Workbook

Sheet COM
H4: 91.6 | J4: 88.4 | L4: 89.3 | N4: 89.5 | P4: 90 | R4: 90.5
A5: Классификация | E5: донор | F5: Наименование проекта | G5: номер и дата кредитного соглашения | H5: 2025 | J5: 2026 | L5: 2027 | N5: 2028 | P5: 2029 | R5: 2030
A6: III | B6: IV | D6: V | H6: Внутреннее | I6: Внешнее | J6: Внутреннее | K6: Внешнее | L6: Внутреннее | M6: Внешнее | N6: Внутреннее | O6: Внешнее | P6: Внутреннее | Q6: Внешнее | R6: Внутреннее | S6: Внешнее
F7: Министерство финансов КР | H7: =H8 -> #REF! | I7: =I8 -> #REF! | J7: =J8 -> #REF! | K7: =K8 -> #REF! | L7: =L8 -> #REF! | M7: =M8 -> #REF! | N7: =N8 -> #REF! | O7: =O8 -> #REF! | ... S7: =S8 -> #REF! | T7: =I7+K7+M7+O7+Q7+S7 -> #REF!
F8: Государственные инвестиции | H8: =SUM(H9:H38) -> #REF! | I8: =SUM(I9:I38) -> #REF! | J8: =SUM(J9:J38) -> #REF! | K8: =SUM(K9:K38) -> #REF! | L8: =SUM(L9:L38) -> #REF! | M8: =SUM(M9:M38) -> #REF! | N8: =SUM(N9:N38) -> #REF! | O8: =SUM(O9:O38) -> #REF! | ... S8: =SUM(S9:S38) -> #REF! | T8: =I8+K8+M8+O8+Q8+S8 -> #REF!
A9: 311 | B9: 25 | C9: 910 | D9: 70499 | F9: Цепочка добавленной стоимости агрофинансирования (КфВ) Фаза 2 | H9: =#REF!*COM!$H$4 -> #REF! | I9: =#REF!*COM!$H$4 -> #REF! | J9: =#REF!*COM!$J$4 -> #REF! | K9: =#REF!*COM!$J$4 -> #REF! | L9: =#REF!*COM!$L$4 -> #REF! | M9: =#REF!*COM!$L$4 -> #REF! | N9: =#REF!*COM!$N$4 -> #REF! | O9: =#REF!*COM!$N$4 -> #REF! | P9: =#REF!*COM!$P$4 -> #REF! | Q9: =#REF!*COM!$P$4 -> #REF! | R9: =#REF!*COM!$R$4 -> #REF! | S9: =#REF!*COM!$R$4 -> #REF! | T9: =I9+K9+M9+O9+Q9+S9 -> #REF!
A10: 311 | B10: 25 | C10: 920 | D10: 70499 | E10: КфВ | F10: Цепочка добавленной стоимости агрофинансирования (КфВ) (грант) Фаза 2 | H10: =#REF!*COM!$H$4 -> #REF! | I10: =#REF!*COM!$H$4 -> #REF! | J10: =#REF!*COM!$J$4 -> #REF! | K10: =#REF!*COM!$J$4 -> #REF! | L10: =#REF!*COM!$L$4 -> #REF! | M10: =#REF!*COM!$L$4 -> #REF! | N10: =#REF!*COM!$N$4 -> #REF! | O10: =#REF!*COM!$N$4 -> #REF! | P10: =#REF!*COM!$P$4 -> #REF! | Q10: =#REF!*COM!$P$4 -> #REF! | R10: =#REF!*COM!$R$4 -> #REF! | S10: =#REF!*COM!$R$4 -> #REF! | T10: =I10+K10+M10+O10+Q10+S10 -> #REF!
A11: 311 | B11: 25 | C11: 910 | D11: 70499 | F11: Цепочка добавленной стоимости агрофинансирования-2 (ИФЦА) | H11: =#REF!*COM!$H$4 -> #REF! | I11: =#REF!*COM!$H$4 -> #REF! | J11: =#REF!*COM!$J$4 -> #REF! | K11: =#REF!*COM!$J$4 -> #REF! | L11: =#REF!*COM!$L$4 -> #REF! | M11: =#REF!*COM!$L$4 -> #REF! | N11: =#REF!*COM!$N$4 -> #REF! | O11: =#REF!*COM!$N$4 -> #REF! | P11: =#REF!*COM!$P$4 -> #REF! | Q11: =#REF!*COM!$P$4 -> #REF! | R11: =#REF!*COM!$R$4 -> #REF! | S11: =#REF!*COM!$R$4 -> #REF! | T11: =I11+K11+M11+O11+Q11+S11 -> #REF!
A12: 311 | B12: 25 | C12: 920 | D12: 70499 | E12: ИФЦА | F12: Цепочка добавленной стоимости агрофинансирования-2 (ИФЦА) (грант) | H12: =#REF!*COM!$H$4 -> #REF! | I12: =#REF!*COM!$H$4 -> #REF! | J12: =#REF!*COM!$J$4 -> #REF! | K12: =#REF!*COM!$J$4 -> #REF! | L12: =#REF!*COM!$L$4 -> #REF! | M12: =#REF!*COM!$L$4 -> #REF! | N12: =#REF!*COM!$N$4 -> #REF! | O12: =#REF!*COM!$N$4 -> #REF! | P12: =#REF!*COM!$P$4 -> #REF! | Q12: =#REF!*COM!$P$4 -> #REF! | R12: =#REF!*COM!$R$4 -> #REF! | S12: =#REF!*COM!$R$4 -> #REF! | T12: =I12+K12+M12+O12+Q12+S12 -> #REF!
A13: 321 | B13: 25 | C13: 930 | D13: 70499 | E13: ЕИБ | F13: Цепочка добавленной стоимости агрофинансирования-2 (ЕИБ) (кредит) | G13: FI № 84.373 | H13: =#REF!*COM!$H$4 -> #REF! | I13: =#REF!*COM!$H$4 -> #REF! | J13: =#REF!*COM!$J$4 -> #REF! | K13: =#REF!*COM!$J$4 -> #REF! | L13: =#REF!*COM!$L$4 -> #REF! | M13: =#REF!*COM!$L$4 -> #REF! | N13: =#REF!*COM!$N$4 -> #REF! | O13: =#REF!*COM!$N$4 -> #REF! | P13: =#REF!*COM!$P$4 -> #REF! | Q13: =#REF!*COM!$P$4 -> #REF! | R13: =#REF!*COM!$R$4 -> #REF! | S13: =#REF!*COM!$R$4 -> #REF! | T13: =I13+K13+M13+O13+Q13+S13 -> #REF!
A14: 311 | B14: 25 | C14: 920 | D14: 70499 | E14: ВБ | F14: Комплексное повышение производительности молочного сектора (ВБ) (грант) Доп. Финансирование | H14: =#REF!*COM!$H$4 -> #REF! | I14: =#REF!*COM!$H$4 -> #REF! | J14: =#REF!*COM!$J$4 -> #REF! | K14: =#REF!*COM!$J$4 -> #REF! | L14: =#REF!*COM!$L$4 -> #REF! | M14: =#REF!*COM!$L$4 -> #REF! | N14: =#REF!*COM!$N$4 -> #REF! | O14: =#REF!*COM!$N$4 -> #REF! | P14: =#REF!*COM!$P$4 -> #REF! | Q14: =#REF!*COM!$P$4 -> #REF! | R14: =#REF!*COM!$R$4 -> #REF! | S14: =#REF!*COM!$R$4 -> #REF! | T14: =I14+K14+M14+O14+Q14+S14 -> #REF!
A15: 321 | B15: 25 | C15: 920 | D15: 70499 | E15: ВБ | F15: Комплексное повышение производительности молочного сектора (ВБ) (грант) Доп. Финансирование | H15: =#REF!*COM!$H$4 -> #REF! | I15: =#REF!*COM!$H$4 -> #REF! | J15: =#REF!*COM!$J$4 -> #REF! | K15: =#REF!*COM!$J$4 -> #REF! | L15: =#REF!*COM!$L$4 -> #REF! | M15: =#REF!*COM!$L$4 -> #REF! | N15: =#REF!*COM!$N$4 -> #REF! | O15: =#REF!*COM!$N$4 -> #REF! | P15: =#REF!*COM!$P$4 -> #REF! | Q15: =#REF!*COM!$P$4 -> #REF! | R15: =#REF!*COM!$R$4 -> #REF! | S15: =#REF!*COM!$R$4 -> #REF! | T15: =I15+K15+M15+O15+Q15+S15 -> #REF!
A16: 311 | B16: 25 | C16: 930 | D16: 70499 | E16: ВБ | F16: Комплексное повышение производительности молочного сектора (ВБ) (кредит) Доп. Финансирование | G16: № 6941-KG | H16: =#REF!*COM!$H$4 -> #REF! | I16: =#REF!*COM!$H$4 -> #REF! | J16: =#REF!*COM!$J$4 -> #REF! | K16: =#REF!*COM!$J$4 -> #REF! | L16: =#REF!*COM!$L$4 -> #REF! | M16: =#REF!*COM!$L$4 -> #REF! | N16: =#REF!*COM!$N$4 -> #REF! | O16: =#REF!*COM!$N$4 -> #REF! | P16: =#REF!*COM!$P$4 -> #REF! | Q16: =#REF!*COM!$P$4 -> #REF! | R16: =#REF!*COM!$R$4 -> #REF! | S16: =#REF!*COM!$R$4 -> #REF! | T16: =I16+K16+M16+O16+Q16+S16 -> #REF!
A17: 321 | B17: 25 | C17: 930 | D17: 70499 | E17: ВБ | F17: Комплексное повышение производительности молочного сектора (ВБ) (кредит) Доп. Финансирование | H17: =#REF!*COM!$H$4 -> #REF! | I17: =#REF!*COM!$H$4 -> #REF! | J17: =#REF!*COM!$J$4 -> #REF! | K17: =#REF!*COM!$J$4 -> #REF! | L17: =#REF!*COM!$L$4 -> #REF! | M17: =#REF!*COM!$L$4 -> #REF! | N17: =#REF!*COM!$N$4 -> #REF! | O17: =#REF!*COM!$N$4 -> #REF! | P17: =#REF!*COM!$P$4 -> #REF! | Q17: =#REF!*COM!$P$4 -> #REF! | R17: =#REF!*COM!$R$4 -> #REF! | S17: =#REF!*COM!$R$4 -> #REF! | T17: =I17+K17+M17+O17+Q17+S17 -> #REF!
A18: 311 | B18: 25 | C18: 920 | D18: 70499 | E18: ВБ | F18: Проект по поддержке частного сектора (ВБ) (грант) | H18: =#REF!*COM!$H$4 -> #REF! | I18: =#REF!*COM!$H$4 -> #REF! | J18: =#REF!*COM!$J$4 -> #REF! | K18: =#REF!*COM!$J$4 -> #REF! | L18: =#REF!*COM!$L$4 -> #REF! | M18: =#REF!*COM!$L$4 -> #REF! | N18: =#REF!*COM!$N$4 -> #REF! | O18: =#REF!*COM!$N$4 -> #REF! | P18: =#REF!*COM!$P$4 -> #REF! | Q18: =#REF!*COM!$P$4 -> #REF! | R18: =#REF!*COM!$R$4 -> #REF! | S18: =#REF!*COM!$R$4 -> #REF! | T18: =I18+K18+M18+O18+Q18+S18 -> #REF!
A19: 321 | B19: 25 | C19: 920 | D19: 70499 | E19: ВБ | F19: Проект по поддержке частного сектора (ВБ) (грант) | H19: =#REF!*COM!$H$4 -> #REF! | I19: =#REF!*COM!$H$4 -> #REF! | J19: =#REF!*COM!$J$4 -> #REF! | K19: =#REF!*COM!$J$4 -> #REF! | L19: =#REF!*COM!$L$4 -> #REF! | M19: =#REF!*COM!$L$4 -> #REF! | N19: =#REF!*COM!$N$4 -> #REF! | O19: =#REF!*COM!$N$4 -> #REF! | P19: =#REF!*COM!$P$4 -> #REF! | Q19: =#REF!*COM!$P$4 -> #REF! | R19: =#REF!*COM!$R$4 -> #REF! | S19: =#REF!*COM!$R$4 -> #REF! | T19: =I19+K19+M19+O19+Q19+S19 -> #REF!
A20: 321 | B20: 25 | C20: 930 | D20: 70499 | E20: ВБ | F20: Проект по поддержке частного сектора (ВБ) (кредит) | G20: № 6758-KG | H20: =#REF!*COM!$H$4 -> #REF! | I20: =#REF!*COM!$H$4 -> #REF! | J20: =#REF!*COM!$J$4 -> #REF! | K20: =#REF!*COM!$J$4 -> #REF! | L20: =#REF!*COM!$L$4 -> #REF! | M20: =#REF!*COM!$L$4 -> #REF! | N20: =#REF!*COM!$N$4 -> #REF! | O20: =#REF!*COM!$N$4 -> #REF! | P20: =#REF!*COM!$P$4 -> #REF! | Q20: =#REF!*COM!$P$4 -> #REF! | R20: =#REF!*COM!$R$4 -> #REF! | S20: =#REF!*COM!$R$4 -> #REF! | T20: =I20+K20+M20+O20+Q20+S20 -> #REF!
A21: 311 | B21: 25 | C21: 930 | D21: 70499 | E21: АБИИ | F21: Проект по поддержке частного сектора (АБИИ) (кредит) | G21: № 0423-А | H21: =#REF!*COM!$H$4 -> #REF! | I21: =#REF!*COM!$H$4 -> #REF! | J21: =#REF!*COM!$J$4 -> #REF! | K21: =#REF!*COM!$J$4 -> #REF! | L21: =#REF!*COM!$L$4 -> #REF! | M21: =#REF!*COM!$L$4 -> #REF! | N21: =#REF!*COM!$N$4 -> #REF! | O21: =#REF!*COM!$N$4 -> #REF! | P21: =#REF!*COM!$P$4 -> #REF! | Q21: =#REF!*COM!$P$4 -> #REF! | R21: =#REF!*COM!$R$4 -> #REF! | S21: =#REF!*COM!$R$4 -> #REF! | T21: =I21+K21+M21+O21+Q21+S21 -> #REF!
A22: 321 | B22: 25 | C22: 930 | D22: 70499 | E22: АБИИ | F22: Проект по поддержке частного сектора (АБИИ) (кредит) | H22: =#REF!*COM!$H$4 -> #REF! | I22: =#REF!*COM!$H$4 -> #REF! | J22: =#REF!*COM!$J$4 -> #REF! | K22: =#REF!*COM!$J$4 -> #REF! | L22: =#REF!*COM!$L$4 -> #REF! | M22: =#REF!*COM!$L$4 -> #REF! | N22: =#REF!*COM!$N$4 -> #REF! | O22: =#REF!*COM!$N$4 -> #REF! | P22: =#REF!*COM!$P$4 -> #REF! | Q22: =#REF!*COM!$P$4 -> #REF! | R22: =#REF!*COM!$R$4 -> #REF! | S22: =#REF!*COM!$R$4 -> #REF! | T22: =I22+K22+M22+O22+Q22+S22 -> #REF!
A23: 311 | B23: 25 | C23: 920 | D23: 70499 | E23: ВБ | F23: Экстренная поддержка микро, малых и средних предприятий ДФ (ВБ) (грант) | H23: =#REF!*COM!$H$4 -> #REF! | I23: =#REF!*COM!$H$4 -> #REF! | J23: =#REF!*COM!$J$4 -> #REF! | K23: =#REF!*COM!$J$4 -> #REF! | L23: =#REF!*COM!$L$4 -> #REF! | M23: =#REF!*COM!$L$4 -> #REF! | N23: =#REF!*COM!$N$4 -> #REF! | O23: =#REF!*COM!$N$4 -> #REF! | P23: =#REF!*COM!$P$4 -> #REF! | Q23: =#REF!*COM!$P$4 -> #REF! | R23: =#REF!*COM!$R$4 -> #REF! | S23: =#REF!*COM!$R$4 -> #REF! | T23: =I23+K23+M23+O23+Q23+S23 -> #REF!
A24: 321 | B24: 25 | C24: 920 | D24: 70499 | E24: ВБ | F24: Экстренная поддержка микро, малых и средних предприятий ДФ (ВБ) (грант) | H24: =#REF!*COM!$H$4 -> #REF! | I24: =#REF!*COM!$H$4 -> #REF! | J24: =#REF!*COM!$J$4 -> #REF! | K24: =#REF!*COM!$J$4 -> #REF! | L24: =#REF!*COM!$L$4 -> #REF! | M24: =#REF!*COM!$L$4 -> #REF! | N24: =#REF!*COM!$N$4 -> #REF! | O24: =#REF!*COM!$N$4 -> #REF! | P24: =#REF!*COM!$P$4 -> #REF! | Q24: =#REF!*COM!$P$4 -> #REF! | R24: =#REF!*COM!$R$4 -> #REF! | S24: =#REF!*COM!$R$4 -> #REF! | T24: =I24+K24+M24+O24+Q24+S24 -> #REF!
A25: 321 | B25: 25 | C25: 930 | D25: 70499 | E25: ВБ | F25: Экстренная поддержка микро, малых и средних предприятий ДФ (ВБ) (кредит) | G25: № 7094-KG | H25: =#REF!*COM!$H$4 -> #REF! | I25: =#REF!*COM!$H$4 -> #REF! | J25: =#REF!*COM!$J$4 -> #REF! | K25: =#REF!*COM!$J$4 -> #REF! | L25: =#REF!*COM!$L$4 -> #REF! | M25: =#REF!*COM!$L$4 -> #REF! | N25: =#REF!*COM!$N$4 -> #REF! | O25: =#REF!*COM!$N$4 -> #REF! | P25: =#REF!*COM!$P$4 -> #REF! | Q25: =#REF!*COM!$P$4 -> #REF! | R25: =#REF!*COM!$R$4 -> #REF! | S25: =#REF!*COM!$R$4 -> #REF! | T25: =I25+K25+M25+O25+Q25+S25 -> #REF!
A26: 311 | B26: 25 | C26: 930 | D26: 70499 | E26: ВБ | F26: Улучшение качества воздуха в городе Бишкек (ВБ) (кредит) | G26: № 7434-KG | H26: =#REF!*COM!$H$4 -> #REF! | I26: =#REF!*COM!$H$4 -> #REF! | J26: =#REF!*COM!$J$4 -> #REF! | K26: =#REF!*COM!$J$4 -> #REF! | L26: =#REF!*COM!$L$4 -> #REF! | M26: =#REF!*COM!$L$4 -> #REF! | N26: =#REF!*COM!$N$4 -> #REF! | O26: =#REF!*COM!$N$4 -> #REF! | P26: =#REF!*COM!$P$4 -> #REF! | Q26: =#REF!*COM!$P$4 -> #REF! | R26: =#REF!*COM!$R$4 -> #REF! | S26: =#REF!*COM!$R$4 -> #REF! | T26: =I26+K26+M26+O26+Q26+S26 -> #REF!
A27: 321 | B27: 25 | C27: 930 | D27: 70499 | E27: ВБ | F27: Улучшение качества воздуха в городе Бишкек (ВБ) (кредит) | H27: =#REF!*COM!$H$4 -> #REF! | I27: =#REF!*COM!$H$4 -> #REF! | J27: =#REF!*COM!$J$4 -> #REF! | K27: =#REF!*COM!$J$4 -> #REF! | L27: =#REF!*COM!$L$4 -> #REF! | M27: =#REF!*COM!$L$4 -> #REF! | N27: =#REF!*COM!$N$4 -> #REF! | O27: =#REF!*COM!$N$4 -> #REF! | P27: =#REF!*COM!$P$4 -> #REF! | Q27: =#REF!*COM!$P$4 -> #REF! | R27: =#REF!*COM!$R$4 -> #REF! | S27: =#REF!*COM!$R$4 -> #REF! | T27: =I27+K27+M27+O27+Q27+S27 -> #REF!
A28: 311 | B28: 25 | C28: 930 | D28: 70499 | E28: ВБ | F28: Проект развития устойчивых агропродовольственных кластеров (ВБ) (кредит) | G28: № 7526-KG | H28: =#REF!*COM!$H$4 -> #REF! | I28: =#REF!*COM!$H$4 -> #REF! | J28: =#REF!*COM!$J$4 -> #REF! | K28: =#REF!*COM!$J$4 -> #REF! | L28: =#REF!*COM!$L$4 -> #REF! | M28: =#REF!*COM!$L$4 -> #REF! | N28: =#REF!*COM!$N$4 -> #REF! | O28: =#REF!*COM!$N$4 -> #REF! | P28: =#REF!*COM!$P$4 -> #REF! | Q28: =#REF!*COM!$P$4 -> #REF! | R28: =#REF!*COM!$R$4 -> #REF! | S28: =#REF!*COM!$R$4 -> #REF! | T28: =I28+K28+M28+O28+Q28+S28 -> #REF!
A29: 321 | B29: 25 | C29: 930 | D29: 70499 | E29: ВБ | F29: Проект развития устойчивых агропродовольственных кластеров (ВБ) (кредит) | H29: =#REF!*COM!$H$4 -> #REF! | I29: =#REF!*COM!$H$4 -> #REF! | J29: =#REF!*COM!$J$4 -> #REF! | K29: =#REF!*COM!$J$4 -> #REF! | L29: =#REF!*COM!$L$4 -> #REF! | M29: =#REF!*COM!$L$4 -> #REF! | N29: =#REF!*COM!$N$4 -> #REF! | O29: =#REF!*COM!$N$4 -> #REF! | P29: =#REF!*COM!$P$4 -> #REF! | Q29: =#REF!*COM!$P$4 -> #REF! | R29: =#REF!*COM!$R$4 -> #REF! | S29: =#REF!*COM!$R$4 -> #REF! | T29: =I29+K29+M29+O29+Q29+S29 -> #REF!
A30: 311 | B30: 25 | C30: 930 | D30: 70499 | E30: ВБ | F30: Развитие устойчивых финансовых рынков для микро-, малых и средних предприятий в Кыргызской Республике (ВБ) (кредит) (план) | G30: 7741-KG | H30: =#REF!*COM!$H$4 -> #REF! | I30: =#REF!*COM!$H$4 -> #REF! | J30: =#REF!*COM!$J$4 -> #REF! | K30: =#REF!*COM!$J$4 -> #REF! | L30: =#REF!*COM!$L$4 -> #REF! | M30: =#REF!*COM!$L$4 -> #REF! | N30: =#REF!*COM!$N$4 -> #REF! | O30: =#REF!*COM!$N$4 -> #REF! | P30: =#REF!*COM!$P$4 -> #REF! | Q30: =#REF!*COM!$P$4 -> #REF! | R30: =#REF!*COM!$R$4 -> #REF! | S30: =#REF!*COM!$R$4 -> #REF! | T30: =I30+K30+M30+O30+Q30+S30 -> #REF!
A31: 321 | B31: 25 | C31: 930 | D31: 70499 | E31: ВБ | F31: Развитие устойчивых финансовых рынков для микро-, малых и средних предприятий в Кыргызской Республике (ВБ) (кредит) (план) | H31: =#REF!*COM!$H$4 -> #REF! | I31: =#REF!*COM!$H$4 -> #REF! | J31: =#REF!*COM!$J$4 -> #REF! | K31: =#REF!*COM!$J$4 -> #REF! | L31: =#REF!*COM!$L$4 -> #REF! | M31: =#REF!*COM!$L$4 -> #REF! | N31: =#REF!*COM!$N$4 -> #REF! | O31: =#REF!*COM!$N$4 -> #REF! | P31: =#REF!*COM!$P$4 -> #REF! | Q31: =#REF!*COM!$P$4 -> #REF! | R31: =#REF!*COM!$R$4 -> #REF! | S31: =#REF!*COM!$R$4 -> #REF! | T31: =I31+K31+M31+O31+Q31+S31 -> #REF!
A32: 311 | B32: 25 | C32: 920 | D32: 70499 | E32: ВБ | F32: Проект сельских инвестиций - 3 ДФ (ВБ) (грант) | H32: =#REF!*COM!$H$4 -> #REF! | I32: =#REF!*COM!$H$4 -> #REF! | J32: =#REF!*COM!$J$4 -> #REF! | K32: =#REF!*COM!$J$4 -> #REF! | L32: =#REF!*COM!$L$4 -> #REF! | M32: =#REF!*COM!$L$4 -> #REF! | N32: =#REF!*COM!$N$4 -> #REF! | O32: =#REF!*COM!$N$4 -> #REF! | P32: =#REF!*COM!$P$4 -> #REF! | Q32: =#REF!*COM!$P$4 -> #REF! | R32: =#REF!*COM!$R$4 -> #REF! | S32: =#REF!*COM!$R$4 -> #REF!
A33: 311 | B33: 25 | C33: 930 | D33: 70499 | E33: ВБ | F33: Проект сельских инвестиций - 3 ДФ (ВБ) (кредит) | H33: =#REF!*COM!$H$4 -> #REF! | I33: =#REF!*COM!$H$4 -> #REF! | J33: =#REF!*COM!$J$4 -> #REF! | K33: =#REF!*COM!$J$4 -> #REF! | L33: =#REF!*COM!$L$4 -> #REF! | M33: =#REF!*COM!$L$4 -> #REF! | N33: =#REF!*COM!$N$4 -> #REF! | O33: =#REF!*COM!$N$4 -> #REF! | P33: =#REF!*COM!$P$4 -> #REF! | Q33: =#REF!*COM!$P$4 -> #REF! | R33: =#REF!*COM!$R$4 -> #REF! | S33: =#REF!*COM!$R$4 -> #REF!
T34: =I34+K34+M34+O34+Q34+S34 -> 0
T36: =I36+K36+M36+O36+Q36+S36 -> 0
T37: =I37+K37+M37+O37+Q37+S37 -> 0
T38: =I38+K38+M38+O38+Q38+S38 -> 0
F39: Министерство экономики и коммерции КР | H39: =H40 -> #REF! | I39: =I40 -> #REF! | J39: =J40 -> #REF! | K39: =K40 -> #REF! | L39: =L40 -> #REF! | M39: =M40 -> #REF! | N39: =N40 -> #REF! | O39: =O40 -> #REF! | ... S39: =S40 -> #REF! | T39: =I39+K39+M39+O39+Q39+S39 -> #REF!
F40: Государственные инвестиции | H40: =SUM(H41:H68) -> #REF! | I40: =SUM(I41:I68) -> #REF! | J40: =SUM(J41:J68) -> #REF! | K40: =SUM(K41:K68) -> #REF! | L40: =SUM(L41:L68) -> #REF! | M40: =SUM(M41:M68) -> #REF! | N40: =SUM(N41:N68) -> #REF! | O40: =SUM(O41:O68) -> #REF! | ... S40: =SUM(S41:S68) -> #REF! | T40: =I40+K40+M40+O40+Q40+S40 -> #REF!
A41: 311 | B41: 28 | C41: 920 | D41: 70499 | E41: ВБ | F41: Проект регионального экономического развития Ошской области (ВБ) (грант) | G41: Грант D5700-KG/Кредит 6558-KG | H41: =#REF!*COM!$H$4 -> #REF! | I41: =#REF!*COM!$H$4 -> #REF! | J41: =#REF!*COM!$J$4 -> #REF! | K41: =#REF!*COM!$J$4 -> #REF! | L41: =#REF!*COM!$L$4 -> #REF! | M41: =#REF!*COM!$L$4 -> #REF! | N41: =#REF!*COM!$N$4 -> #REF! | O41: =#REF!*COM!$N$4 -> #REF! | P41: =#REF!*COM!$P$4 -> #REF! | Q41: =#REF!*COM!$P$4 -> #REF! | R41: =#REF!*COM!$R$4 -> #REF! | S41: =#REF!*COM!$R$4 -> #REF! | T41: =I41+K41+M41+O41+Q41+S41 -> #REF!
A42: 311 | B42: 28 | C42: 930 | D42: 70499 | E42: ВБ | F42: Проект регионального экономического развития Ошской области (ВБ) (кредит) | H42: =#REF!*COM!$H$4 -> #REF! | I42: =#REF!*COM!$H$4 -> #REF! | J42: =#REF!*COM!$J$4 -> #REF! | K42: =#REF!*COM!$J$4 -> #REF! | L42: =#REF!*COM!$L$4 -> #REF! | M42: =#REF!*COM!$L$4 -> #REF! | N42: =#REF!*COM!$N$4 -> #REF! | O42: =#REF!*COM!$N$4 -> #REF! | P42: =#REF!*COM!$P$4 -> #REF! | Q42: =#REF!*COM!$P$4 -> #REF! | R42: =#REF!*COM!$R$4 -> #REF! | S42: =#REF!*COM!$R$4 -> #REF! | T42: =I42+K42+M42+O42+Q42+S42 -> #REF!
A43: 311 | B43: 28 | C43: 930 | D43: 70499 | E43: ВБ | F43: Проект регионального экономического развития Ошской области - дополнительное финансирование (ВБ) (кредит) | H43: =#REF!*COM!$H$4 -> #REF! | I43: =#REF!*COM!$H$4 -> #REF! | J43: =#REF!*COM!$J$4 -> #REF! | K43: =#REF!*COM!$J$4 -> #REF! | L43: =#REF!*COM!$L$4 -> #REF! | M43: =#REF!*COM!$L$4 -> #REF! | N43: =#REF!*COM!$N$4 -> #REF! | O43: =#REF!*COM!$N$4 -> #REF! | P43: =#REF!*COM!$P$4 -> #REF! | Q43: =#REF!*COM!$P$4 -> #REF! | R43: =#REF!*COM!$R$4 -> #REF! | S43: =#REF!*COM!$R$4 -> #REF! | T43: =I43+K43+M43+O43+Q43+S43 -> #REF!
A44: 311 | B44: 28 | C44: 920 | D44: 70499 | E44: ВБ | F44: Проект регионального экономического развития Баткенской области (ВБ) (грант) | G44: Грант D976-KG/Кредит 70490-KG | H44: =#REF!*COM!$H$4 -> #REF! | I44: =#REF!*COM!$H$4 -> #REF! | J44: =#REF!*COM!$J$4 -> #REF! | K44: =#REF!*COM!$J$4 -> #REF! | L44: =#REF!*COM!$L$4 -> #REF! | M44: =#REF!*COM!$L$4 -> #REF! | N44: =#REF!*COM!$N$4 -> #REF! | O44: =#REF!*COM!$N$4 -> #REF! | P44: =#REF!*COM!$P$4 -> #REF! | Q44: =#REF!*COM!$P$4 -> #REF! | R44: =#REF!*COM!$R$4 -> #REF! | S44: =#REF!*COM!$R$4 -> #REF! | T44: =I44+K44+M44+O44+Q44+S44 -> #REF!
A45: 311 | B45: 28 | C45: 930 | D45: 70499 | E45: ВБ | F45: Проект регионального экономического развития Баткенской области (ВБ) (кредит) | H45: =#REF!*COM!$H$4 -> #REF! | I45: =#REF!*COM!$H$4 -> #REF! | J45: =#REF!*COM!$J$4 -> #REF! | K45: =#REF!*COM!$J$4 -> #REF! | L45: =#REF!*COM!$L$4 -> #REF! | M45: =#REF!*COM!$L$4 -> #REF! | N45: =#REF!*COM!$N$4 -> #REF! | O45: =#REF!*COM!$N$4 -> #REF! | P45: =#REF!*COM!$P$4 -> #REF! | Q45: =#REF!*COM!$P$4 -> #REF! | R45: =#REF!*COM!$R$4 -> #REF! | S45: =#REF!*COM!$R$4 -> #REF! | T45: =I45+K45+M45+O45+Q45+S45 -> #REF!
A46: 311 | B46: 28 | C46: 920 | D46: 70499 | E46: ВБ | F46: Национальный проект по инициативе сообществ (ВБ) (грант) | G46: Грант D976-KG, Кредит 7049-KG | H46: =#REF!*COM!$H$4 -> #REF! | I46: =#REF!*COM!$H$4 -> #REF! | J46: =#REF!*COM!$J$4 -> #REF! | K46: =#REF!*COM!$J$4 -> #REF! | L46: =#REF!*COM!$L$4 -> #REF! | M46: =#REF!*COM!$L$4 -> #REF! | N46: =#REF!*COM!$N$4 -> #REF! | O46: =#REF!*COM!$N$4 -> #REF! | P46: =#REF!*COM!$P$4 -> #REF! | Q46: =#REF!*COM!$P$4 -> #REF! | R46: =#REF!*COM!$R$4 -> #REF! | S46: =#REF!*COM!$R$4 -> #REF! | T46: =I46+K46+M46+O46+Q46+S46 -> #REF!
A47: 311 | B47: 28 | C47: 930 | D47: 70499 | E47: ВБ | F47: Национальный проект по инициативе сообществ (ВБ) (кредит) | H47: =#REF!*COM!$H$4 -> #REF! | I47: =#REF!*COM!$H$4 -> #REF! | J47: =#REF!*COM!$J$4 -> #REF! | K47: =#REF!*COM!$J$4 -> #REF! | L47: =#REF!*COM!$L$4 -> #REF! | M47: =#REF!*COM!$L$4 -> #REF! | N47: =#REF!*COM!$N$4 -> #REF! | O47: =#REF!*COM!$N$4 -> #REF! | P47: =#REF!*COM!$P$4 -> #REF! | Q47: =#REF!*COM!$P$4 -> #REF! | R47: =#REF!*COM!$R$4 -> #REF! | S47: =#REF!*COM!$R$4 -> #REF! | T47: =I47+K47+M47+O47+Q47+S47 -> #REF!
A48: 311 | B48: 28 | C48: 910 | D48: 70499 | F48: Деятельность «Развитие центра бизнес-услуг», SEFF 2 (АБР) (план) | H48: =#REF!*COM!$H$4 -> #REF! | I48: =#REF!*COM!$H$4 -> #REF! | J48: =#REF!*COM!$J$4 -> #REF! | K48: =#REF!*COM!$J$4 -> #REF! | L48: =#REF!*COM!$L$4 -> #REF! | M48: =#REF!*COM!$L$4 -> #REF! | N48: =#REF!*COM!$N$4 -> #REF! | O48: =#REF!*COM!$N$4 -> #REF! | P48: =#REF!*COM!$P$4 -> #REF! | Q48: =#REF!*COM!$P$4 -> #REF! | R48: =#REF!*COM!$R$4 -> #REF! | S48: =#REF!*COM!$R$4 -> #REF!
A49: 311 | B49: 28 | C49: 920 | D49: 70499 | E49: АБР | F49: Деятельность «Развитие центра бизнес-услуг», SEFF 2 (АБР) (грант) (план) | H49: =#REF!*COM!$H$4 -> #REF! | I49: =#REF!*COM!$H$4 -> #REF! | J49: =#REF!*COM!$J$4 -> #REF! | K49: =#REF!*COM!$J$4 -> #REF! | L49: =#REF!*COM!$L$4 -> #REF! | M49: =#REF!*COM!$L$4 -> #REF! | N49: =#REF!*COM!$N$4 -> #REF! | O49: =#REF!*COM!$N$4 -> #REF! | P49: =#REF!*COM!$P$4 -> #REF! | Q49: =#REF!*COM!$P$4 -> #REF! | R49: =#REF!*COM!$R$4 -> #REF! | S49: =#REF!*COM!$R$4 -> #REF!
A50: 311 | B50: 28 | C50: 910 | D50: 70499 | F50: Энергоэффективность в общественных зданиях (АБР) (план) | H50: =#REF!*COM!$H$4 -> #REF! | I50: =#REF!*COM!$H$4 -> #REF! | J50: =#REF!*COM!$J$4 -> #REF! | K50: =#REF!*COM!$J$4 -> #REF! | L50: =#REF!*COM!$L$4 -> #REF! | M50: =#REF!*COM!$L$4 -> #REF! | N50: =#REF!*COM!$N$4 -> #REF! | O50: =#REF!*COM!$N$4 -> #REF! | P50: =#REF!*COM!$P$4 -> #REF! | Q50: =#REF!*COM!$P$4 -> #REF! | R50: =#REF!*COM!$R$4 -> #REF! | S50: =#REF!*COM!$R$4 -> #REF!
A51: 311 | B51: 28 | C51: 920 | D51: 70499 | E51: АБР | F51: Энергоэффективность в общественных зданиях (АБР) (грант) (план) | H51: =#REF!*COM!$H$4 -> #REF! | I51: =#REF!*COM!$H$4 -> #REF! | J51: =#REF!*COM!$J$4 -> #REF! | K51: =#REF!*COM!$J$4 -> #REF! | L51: =#REF!*COM!$L$4 -> #REF! | M51: =#REF!*COM!$L$4 -> #REF! | N51: =#REF!*COM!$N$4 -> #REF! | O51: =#REF!*COM!$N$4 -> #REF! | P51: =#REF!*COM!$P$4 -> #REF! | Q51: =#REF!*COM!$P$4 -> #REF! | R51: =#REF!*COM!$R$4 -> #REF! | S51: =#REF!*COM!$R$4 -> #REF!
A52: 311 | B52: 28 | C52: 930 | D52: 70499 | E52: АБР | F52: Энергоэффективность в общественных зданиях (АБР) (кредит) (план) | H52: =#REF!*COM!$H$4 -> #REF! | I52: =#REF!*COM!$H$4 -> #REF! | J52: =#REF!*COM!$J$4 -> #REF! | K52: =#REF!*COM!$J$4 -> #REF! | L52: =#REF!*COM!$L$4 -> #REF! | M52: =#REF!*COM!$L$4 -> #REF! | N52: =#REF!*COM!$N$4 -> #REF! | O52: =#REF!*COM!$N$4 -> #REF! | P52: =#REF!*COM!$P$4 -> #REF! | Q52: =#REF!*COM!$P$4 -> #REF! | R52: =#REF!*COM!$R$4 -> #REF! | S52: =#REF!*COM!$R$4 -> #REF!
A53: 311 | B53: 28 | C53: 920 | D53: 70499 | E53: КфВ | F53: Программа жилищного финансирования (КфВ) (грант) | H53: =#REF!*COM!$H$4 -> #REF! | I53: =#REF!*COM!$H$4 -> #REF! | J53: =#REF!*COM!$J$4 -> #REF! | K53: =#REF!*COM!$J$4 -> #REF! | L53: =#REF!*COM!$L$4 -> #REF! | M53: =#REF!*COM!$L$4 -> #REF! | N53: =#REF!*COM!$N$4 -> #REF! | O53: =#REF!*COM!$N$4 -> #REF! | P53: =#REF!*COM!$P$4 -> #REF! | Q53: =#REF!*COM!$P$4 -> #REF! | R53: =#REF!*COM!$R$4 -> #REF! | S53: =#REF!*COM!$R$4 -> #REF! | T53: =I53+K53+M53+O53+Q53+S53 -> #REF!
A54: 311 | B54: 28 | C54: 920 | D54: 70499 | E54: КфВ | F54: Программа жилищного финансирования (КфВ) (грант) Фаза 2 (план) | H54: =#REF!*COM!$H$4 -> #REF! | I54: =#REF!*COM!$H$4 -> #REF! | J54: =#REF!*COM!$J$4 -> #REF! | K54: =#REF!*COM!$J$4 -> #REF! | L54: =#REF!*COM!$L$4 -> #REF! | M54: =#REF!*COM!$L$4 -> #REF! | N54: =#REF!*COM!$N$4 -> #REF! | O54: =#REF!*COM!$N$4 -> #REF! | P54: =#REF!*COM!$P$4 -> #REF! | Q54: =#REF!*COM!$P$4 -> #REF! | R54: =#REF!*COM!$R$4 -> #REF! | S54: =#REF!*COM!$R$4 -> #REF! | T54: =I54+K54+M54+O54+Q54+S54 -> #REF!
A55: 311 | B55: 28 | C55: 910 | D55: 70499 | F55: Строительство многоэтажных социальных жилых домов (СФР) | H55: =#REF!*COM!$H$4 -> #REF! | I55: =#REF!*COM!$H$4 -> #REF! | J55: =#REF!*COM!$J$4 -> #REF! | K55: =#REF!*COM!$J$4 -> #REF! | L55: =#REF!*COM!$L$4 -> #REF! | M55: =#REF!*COM!$L$4 -> #REF! | N55: =#REF!*COM!$N$4 -> #REF! | O55: =#REF!*COM!$N$4 -> #REF! | P55: =#REF!*COM!$P$4 -> #REF! | Q55: =#REF!*COM!$P$4 -> #REF! | R55: =#REF!*COM!$R$4 -> #REF! | S55: =#REF!*COM!$R$4 -> #REF!
A56: 321 | B56: 28 | C56: 930 | D56: 70499 | E56: СФР | F56: Строительство многоэтажных социальных жилых домов (СФР) (кредит) | G56: 09/789 | H56: =#REF!*COM!$H$4 -> #REF! | I56: =#REF!*COM!$H$4 -> #REF! | J56: =#REF!*COM!$J$4 -> #REF! | K56: =#REF!*COM!$J$4 -> #REF! | L56: =#REF!*COM!$L$4 -> #REF! | M56: =#REF!*COM!$L$4 -> #REF! | N56: =#REF!*COM!$N$4 -> #REF! | O56: =#REF!*COM!$N$4 -> #REF! | P56: =#REF!*COM!$P$4 -> #REF! | Q56: =#REF!*COM!$P$4 -> #REF! | R56: =#REF!*COM!$R$4 -> #REF! | S56: =#REF!*COM!$R$4 -> #REF! | T56: =I56+K56+M56+O56+Q56+S56 -> #REF!
A57: 311 | B57: 28 | C57: 910 | D57: 70499 | F57: Финансирование доступного жилья по стандартам шариата (ИБР) | H57: =#REF!*COM!$H$4 -> #REF! | I57: =#REF!*COM!$H$4 -> #REF! | J57: =#REF!*COM!$J$4 -> #REF! | K57: =#REF!*COM!$J$4 -> #REF! | L57: =#REF!*COM!$L$4 -> #REF! | M57: =#REF!*COM!$L$4 -> #REF! | N57: =#REF!*COM!$N$4 -> #REF! | O57: =#REF!*COM!$N$4 -> #REF! | P57: =#REF!*COM!$P$4 -> #REF! | Q57: =#REF!*COM!$P$4 -> #REF! | R57: =#REF!*COM!$R$4 -> #REF! | S57: =#REF!*COM!$R$4 -> #REF!
A58: 311 | B58: 28 | C58: 930 | D58: 70499 | E58: ИБР | F58: Финансирование доступного жилья по стандартам шариата (ИБР) (кредит) | G58: KGZ-1028 | H58: =#REF!*COM!$H$4 -> #REF! | I58: =#REF!*COM!$H$4 -> #REF! | J58: =#REF!*COM!$J$4 -> #REF! | K58: =#REF!*COM!$J$4 -> #REF! | L58: =#REF!*COM!$L$4 -> #REF! | M58: =#REF!*COM!$L$4 -> #REF! | N58: =#REF!*COM!$N$4 -> #REF! | O58: =#REF!*COM!$N$4 -> #REF! | P58: =#REF!*COM!$P$4 -> #REF! | Q58: =#REF!*COM!$P$4 -> #REF! | R58: =#REF!*COM!$R$4 -> #REF! | S58: =#REF!*COM!$R$4 -> #REF! | T58: =I58+K58+M58+O58+Q58+S58 -> #REF!
A59: 321 | B59: 28 | C59: 930 | D59: 70499 | E59: ИБР | F59: Финансирование доступного жилья по стандартам шариата (ИБР) (кредит) | H59: =#REF!*COM!$H$4 -> #REF! | I59: =#REF!*COM!$H$4 -> #REF! | J59: =#REF!*COM!$J$4 -> #REF! | K59: =#REF!*COM!$J$4 -> #REF! | L59: =#REF!*COM!$L$4 -> #REF! | M59: =#REF!*COM!$L$4 -> #REF! | N59: =#REF!*COM!$N$4 -> #REF! | O59: =#REF!*COM!$N$4 -> #REF! | P59: =#REF!*COM!$P$4 -> #REF! | Q59: =#REF!*COM!$P$4 -> #REF! | R59: =#REF!*COM!$R$4 -> #REF! | S59: =#REF!*COM!$R$4 -> #REF! | T59: =I59+K59+M59+O59+Q59+S59 -> #REF!
A60: 311 | B60: 28 | C60: 910 | D60: 70499 | F60: Расширение доступа к доступному и энергоэффективному жилью (АБР) (план) | H60: =#REF!*COM!$H$4 -> #REF! | I60: =#REF!*COM!$H$4 -> #REF! | J60: =#REF!*COM!$J$4 -> #REF! | K60: =#REF!*COM!$J$4 -> #REF! | L60: =#REF!*COM!$L$4 -> #REF! | M60: =#REF!*COM!$L$4 -> #REF! | N60: =#REF!*COM!$N$4 -> #REF! | O60: =#REF!*COM!$N$4 -> #REF! | P60: =#REF!*COM!$P$4 -> #REF! | Q60: =#REF!*COM!$P$4 -> #REF! | R60: =#REF!*COM!$R$4 -> #REF! | S60: =#REF!*COM!$R$4 -> #REF!
A61: 321 | B61: 28 | C61: 920 | D61: 70499 | E61: АБР | F61: Расширение доступа к доступному и энергоэффективному жилью (АБР) (грант) (план) | H61: =#REF!*COM!$H$4 -> #REF! | I61: =#REF!*COM!$H$4 -> #REF! | J61: =#REF!*COM!$J$4 -> #REF! | K61: =#REF!*COM!$J$4 -> #REF! | L61: =#REF!*COM!$L$4 -> #REF! | M61: =#REF!*COM!$L$4 -> #REF! | N61: =#REF!*COM!$N$4 -> #REF! | O61: =#REF!*COM!$N$4 -> #REF! | P61: =#REF!*COM!$P$4 -> #REF! | Q61: =#REF!*COM!$P$4 -> #REF! | R61: =#REF!*COM!$R$4 -> #REF! | S61: =#REF!*COM!$R$4 -> #REF! | T61: =I61+K61+M61+O61+Q61+S61 -> #REF!
A62: 321 | B62: 28 | C62: 930 | D62: 70499 | E62: АБР | F62: Расширение доступа к доступному и энергоэффективному жилью (АБР) (кредит) (план) | H62: =#REF!*COM!$H$4 -> #REF! | I62: =#REF!*COM!$H$4 -> #REF! | J62: =#REF!*COM!$J$4 -> #REF! | K62: =#REF!*COM!$J$4 -> #REF! | L62: =#REF!*COM!$L$4 -> #REF! | M62: =#REF!*COM!$L$4 -> #REF! | N62: =#REF!*COM!$N$4 -> #REF! | O62: =#REF!*COM!$N$4 -> #REF! | P62: =#REF!*COM!$P$4 -> #REF! | Q62: =#REF!*COM!$P$4 -> #REF! | R62: =#REF!*COM!$R$4 -> #REF! | S62: =#REF!*COM!$R$4 -> #REF! | T62: =I62+K62+M62+O62+Q62+S62 -> #REF!
A63: 321 | B63: 28 | C63: 930 | D63: 70499 | E63: EDCF | F63: Строительство социального жилья (EDCF) (кредит) (план) | H63: =#REF!*COM!$H$4 -> #REF! | I63: =#REF!*COM!$H$4 -> #REF! | J63: =#REF!*COM!$J$4 -> #REF! | K63: =#REF!*COM!$J$4 -> #REF! | L63: =#REF!*COM!$L$4 -> #REF! | M63: =#REF!*COM!$L$4 -> #REF! | N63: =#REF!*COM!$N$4 -> #REF! | O63: =#REF!*COM!$N$4 -> #REF! | P63: =#REF!*COM!$P$4 -> #REF! | Q63: =#REF!*COM!$P$4 -> #REF! | R63: =#REF!*COM!$R$4 -> #REF! | S63: =#REF!*COM!$R$4 -> #REF!
T67: =I67+K67+M67+O67+Q67+S67 -> 0
T68: =I68+K68+M68+O68+Q68+S68 -> 0
F69: Государственная налоговая служба при Министерстве финансов КР | H69: =H70 -> #REF! | I69: =I70 -> #REF! | J69: =J70 -> #REF! | K69: =K70 -> #REF! | L69: =L70 -> #REF! | M69: =M70 -> #REF! | N69: =N70 -> #REF! | O69: =O70 -> #REF! | ... S69: =S70 -> #REF! | T69: =I69+K69+M69+O69+Q69+S69 -> #REF!
F70: Государственные инвестиции | H70: =SUM(H71:H72) -> #REF! | I70: =SUM(I71:I72) -> #REF! | J70: =SUM(J71:J72) -> #REF! | K70: =SUM(K71:K72) -> #REF! | L70: =SUM(L71:L72) -> #REF! | M70: =SUM(M71:M72) -> #REF! | N70: =SUM(N71:N72) -> #REF! | O70: =SUM(O71:O72) -> #REF! | ... S70: =SUM(S71:S72) -> #REF! | T70: =I70+K70+M70+O70+Q70+S70 -> #REF!
A71: 311 | B71: 25 | C71: 920 | D71: 70499 | E71: ВБ | F71: Модернизация системы налогового администрирования и статистической системы (ВБ) (грант) | H71: =#REF!*COM!$H$4 -> #REF! | I71: =#REF!*COM!$H$4 -> #REF! | J71: =#REF!*COM!$J$4 -> #REF! | K71: =#REF!*COM!$J$4 -> #REF! | L71: =#REF!*COM!$L$4 -> #REF! | M71: =#REF!*COM!$L$4 -> #REF! | N71: =#REF!*COM!$N$4 -> #REF! | O71: =#REF!*COM!$N$4 -> #REF! | P71: =#REF!*COM!$P$4 -> #REF! | Q71: =#REF!*COM!$P$4 -> #REF! | R71: =#REF!*COM!$R$4 -> #REF! | S71: =#REF!*COM!$R$4 -> #REF! | T71: =I71+K71+M71+O71+Q71+S71 -> #REF!
A72: 311 | B72: 25 | C72: 930 | D72: 70499 | E72: ВБ | F72: Модернизация системы налогового администрирования и статистической системы (ВБ) (кредит) | G72: 6546-KG | H72: =#REF!*COM!$H$4 -> #REF! | I72: =#REF!*COM!$H$4 -> #REF! | J72: =#REF!*COM!$J$4 -> #REF! | K72: =#REF!*COM!$J$4 -> #REF! | L72: =#REF!*COM!$L$4 -> #REF! | M72: =#REF!*COM!$L$4 -> #REF! | N72: =#REF!*COM!$N$4 -> #REF! | O72: =#REF!*COM!$N$4 -> #REF! | P72: =#REF!*COM!$P$4 -> #REF! | Q72: =#REF!*COM!$P$4 -> #REF! | R72: =#REF!*COM!$R$4 -> #REF! | S72: =#REF!*COM!$R$4 -> #REF! | T72: =I72+K72+M72+O72+Q72+S72 -> #REF!
T73: =I73+K73+M73+O73+Q73+S73 -> 0
T74: =I74+K74+M74+O74+Q74+S74 -> 0
T75: =I75+K75+M75+O75+Q75+S75 -> 0
T76: =I76+K76+M76+O76+Q76+S76 -> 0
T77: =I77+K77+M77+O77+Q77+S77 -> 0
F78: Министерство образования и науки КР | H78: =H79 -> #REF! | I78: =I79 -> #REF! | J78: =J79 -> #REF! | K78: =K79 -> #REF! | L78: =L79 -> #REF! | M78: =M79 -> #REF! | N78: =N79 -> #REF! | O78: =O79 -> #REF! | ... S78: =S79 -> #REF! | T78: =I78+K78+M78+O78+Q78+S78 -> #REF!
F79: Государственные инвестиции | H79: =SUM(H80:H94) -> #REF! | I79: =SUM(I80:I94) -> #REF! | J79: =SUM(J80:J94) -> #REF! | K79: =SUM(K80:K94) -> #REF! | L79: =SUM(L80:L94) -> #REF! | M79: =SUM(M80:M94) -> #REF! | N79: =SUM(N80:N94) -> #REF! | O79: =SUM(O80:O94) -> #REF! | ... S79: =SUM(S80:S94) -> #REF! | T79: =I79+K79+M79+O79+Q79+S79 -> #REF!
A80: 311 | B80: 34 | C80: 920 | D80: 70989 | E80: ВБ | F80: Образование для будущего (ВБ) (грант) | H80: =#REF!*COM!$H$4 -> #REF! | I80: =#REF!*COM!$H$4 -> #REF! | J80: =#REF!*COM!$J$4 -> #REF! | K80: =#REF!*COM!$J$4 -> #REF! | L80: =#REF!*COM!$L$4 -> #REF! | M80: =#REF!*COM!$L$4 -> #REF! | N80: =#REF!*COM!$N$4 -> #REF! | O80: =#REF!*COM!$N$4 -> #REF! | P80: =#REF!*COM!$P$4 -> #REF! | Q80: =#REF!*COM!$P$4 -> #REF! | R80: =#REF!*COM!$R$4 -> #REF! | S80: =#REF!*COM!$R$4 -> #REF! | T80: =I80+K80+M80+O80+Q80+S80 -> #REF!
A81: 311 | B81: 34 | C81: 930 | D81: 70989 | E81: ВБ | F81: Образование для будущего (ВБ) (кредит) | G81: 6563-KG | H81: =#REF!*COM!$H$4 -> #REF! | I81: =#REF!*COM!$H$4 -> #REF! | J81: =#REF!*COM!$J$4 -> #REF! | K81: =#REF!*COM!$J$4 -> #REF! | L81: =#REF!*COM!$L$4 -> #REF! | M81: =#REF!*COM!$L$4 -> #REF! | N81: =#REF!*COM!$N$4 -> #REF! | O81: =#REF!*COM!$N$4 -> #REF! | P81: =#REF!*COM!$P$4 -> #REF! | Q81: =#REF!*COM!$P$4 -> #REF! | R81: =#REF!*COM!$R$4 -> #REF! | S81: =#REF!*COM!$R$4 -> #REF! | T81: =I81+K81+M81+O81+Q81+S81 -> #REF!
A82: 311 | B82: 34 | C82: 920 | D82: 70989 | E82: ВБ | F82: Укрепление основ обучения (ВБ) (грант) | H82: =#REF!*COM!$H$4 -> #REF! | I82: =#REF!*COM!$H$4 -> #REF! | J82: =#REF!*COM!$J$4 -> #REF! | K82: =#REF!*COM!$J$4 -> #REF! | L82: =#REF!*COM!$L$4 -> #REF! | M82: =#REF!*COM!$L$4 -> #REF! | N82: =#REF!*COM!$N$4 -> #REF! | O82: =#REF!*COM!$N$4 -> #REF! | P82: =#REF!*COM!$P$4 -> #REF! | Q82: =#REF!*COM!$P$4 -> #REF! | R82: =#REF!*COM!$R$4 -> #REF! | S82: =#REF!*COM!$R$4 -> #REF! | T82: =I82+K82+M82+O82+Q82+S82 -> #REF!
A83: 311 | B83: 34 | C83: 910 | D83: 70989 | F83: Программа развития сектора: реформирование системы школьного образования (АБР) (план) | H83: =#REF!*COM!$H$4 -> #REF! | I83: =#REF!*COM!$H$4 -> #REF! | J83: =#REF!*COM!$J$4 -> #REF! | K83: =#REF!*COM!$J$4 -> #REF! | L83: =#REF!*COM!$L$4 -> #REF! | M83: =#REF!*COM!$L$4 -> #REF! | N83: =#REF!*COM!$N$4 -> #REF! | O83: =#REF!*COM!$N$4 -> #REF! | P83: =#REF!*COM!$P$4 -> #REF! | Q83: =#REF!*COM!$P$4 -> #REF! | R83: =#REF!*COM!$R$4 -> #REF! | S83: =#REF!*COM!$R$4 -> #REF! | T83: =I83+K83+M83+O83+Q83+S83 -> #REF!
A84: 311 | B84: 34 | C84: 920 | D84: 70989 | E84: АБР | F84: Программа развития сектора: реформирование сектора школьного образования (АБР) (грант) (план) | G84: №0851 | H84: =#REF!*COM!$H$4 -> #REF! | I84: =#REF!*COM!$H$4 -> #REF! | J84: =#REF!*COM!$J$4 -> #REF! | K84: =#REF!*COM!$J$4 -> #REF! | L84: =#REF!*COM!$L$4 -> #REF! | M84: =#REF!*COM!$L$4 -> #REF! | N84: =#REF!*COM!$N$4 -> #REF! | O84: =#REF!*COM!$N$4 -> #REF! | P84: =#REF!*COM!$P$4 -> #REF! | Q84: =#REF!*COM!$P$4 -> #REF! | R84: =#REF!*COM!$R$4 -> #REF! | S84: =#REF!*COM!$R$4 -> #REF! | T84: =I84+K84+M84+O84+Q84+S84 -> #REF!
A85: 311 | B85: 34 | C85: 930 | D85: 70989 | E85: АБР | F85: Программа развития сектора: реформирование сектора школьного образования (АБР) (кредит) (план) | G85: №4217 | H85: =#REF!*COM!$H$4 -> #REF! | I85: =#REF!*COM!$H$4 -> #REF! | J85: =#REF!*COM!$J$4 -> #REF! | K85: =#REF!*COM!$J$4 -> #REF! | L85: =#REF!*COM!$L$4 -> #REF! | M85: =#REF!*COM!$L$4 -> #REF! | N85: =#REF!*COM!$N$4 -> #REF! | O85: =#REF!*COM!$N$4 -> #REF! | P85: =#REF!*COM!$P$4 -> #REF! | Q85: =#REF!*COM!$P$4 -> #REF! | R85: =#REF!*COM!$R$4 -> #REF! | S85: =#REF!*COM!$R$4 -> #REF! | T85: =I85+K85+M85+O85+Q85+S85 -> #REF!
A86: 311 | B86: 34 | C86: 930 | D86: 70989 | E86: ВБ | F86: Качество высшего образования и инновации (ВБ) (кредит) (план) | G86: 7480-KG | H86: =#REF!*COM!$H$4 -> #REF! | I86: =#REF!*COM!$H$4 -> #REF! | J86: =#REF!*COM!$J$4 -> #REF! | K86: =#REF!*COM!$J$4 -> #REF! | L86: =#REF!*COM!$L$4 -> #REF! | M86: =#REF!*COM!$L$4 -> #REF! | N86: =#REF!*COM!$N$4 -> #REF! | O86: =#REF!*COM!$N$4 -> #REF! | P86: =#REF!*COM!$P$4 -> #REF! | Q86: =#REF!*COM!$P$4 -> #REF! | R86: =#REF!*COM!$R$4 -> #REF! | S86: =#REF!*COM!$R$4 -> #REF! | T86: =I86+K86+M86+O86+Q86+S86 -> #REF!
A87: 311 | B87: 34 | C87: 920 | D87: 70989 | E87: ЕФСР | F87: Smart-Ed по улучшению доступа к возможностям инклюзивного обучения и его качества для всех детей в Кыргызской Республике» (ЕФСР) (грант) | H87: =#REF!*COM!$H$4 -> #REF! | I87: =#REF!*COM!$H$4 -> #REF! | J87: =#REF!*COM!$J$4 -> #REF! | K87: =#REF!*COM!$J$4 -> #REF! | L87: =#REF!*COM!$L$4 -> #REF! | M87: =#REF!*COM!$L$4 -> #REF! | N87: =#REF!*COM!$N$4 -> #REF! | O87: =#REF!*COM!$N$4 -> #REF! | P87: =#REF!*COM!$P$4 -> #REF! | Q87: =#REF!*COM!$P$4 -> #REF! | R87: =#REF!*COM!$R$4 -> #REF! | S87: =#REF!*COM!$R$4 -> #REF! | T87: =I87+K87+M87+O87+Q87+S87 -> #REF!
A88: 311 | B88: 34 | C88: 920 | D88: 70989 | E88: ИБР | F88: Smart-Ed по улучшению доступа к возможностям инклюзивного обучения и его качества для всех детей в Кыргызской Республике» (ИБР) (грант) | H88: =#REF!*COM!$H$4 -> #REF! | I88: =#REF!*COM!$H$4 -> #REF! | J88: =#REF!*COM!$J$4 -> #REF! | K88: =#REF!*COM!$J$4 -> #REF! | L88: =#REF!*COM!$L$4 -> #REF! | M88: =#REF!*COM!$L$4 -> #REF! | N88: =#REF!*COM!$N$4 -> #REF! | O88: =#REF!*COM!$N$4 -> #REF! | P88: =#REF!*COM!$P$4 -> #REF! | Q88: =#REF!*COM!$P$4 -> #REF! | R88: =#REF!*COM!$R$4 -> #REF! | S88: =#REF!*COM!$R$4 -> #REF!
A89: 311 | B89: 34 | C89: 930 | D89: 70989 | E89: ИБР | F89: Smart-Ed по улучшению доступа к возможностям инклюзивного обучения и его качества для всех детей в Кыргызской Республике» (ИБР) (кредит) | H89: =#REF!*COM!$H$4 -> #REF! | I89: =#REF!*COM!$H$4 -> #REF! | J89: =#REF!*COM!$J$4 -> #REF! | K89: =#REF!*COM!$J$4 -> #REF! | L89: =#REF!*COM!$L$4 -> #REF! | M89: =#REF!*COM!$L$4 -> #REF! | N89: =#REF!*COM!$N$4 -> #REF! | O89: =#REF!*COM!$N$4 -> #REF! | P89: =#REF!*COM!$P$4 -> #REF! | Q89: =#REF!*COM!$P$4 -> #REF! | R89: =#REF!*COM!$R$4 -> #REF! | S89: =#REF!*COM!$R$4 -> #REF! | T89: =I89+K89+M89+O89+Q89+S89 -> #REF!
A90: 311 | B90: 34 | C90: 920 | D90: 70989 | E90: ГПЦО | F90: Smart-Ed по улучшению доступа к возможностям инклюзивного обучения и его качества для всех детей в Кыргызской Республике» | H90: =#REF!*COM!$H$4 -> #REF! | I90: =#REF!*COM!$H$4 -> #REF! | J90: =#REF!*COM!$J$4 -> #REF! | K90: =#REF!*COM!$J$4 -> #REF! | L90: =#REF!*COM!$L$4 -> #REF! | M90: =#REF!*COM!$L$4 -> #REF! | N90: =#REF!*COM!$N$4 -> #REF! | O90: =#REF!*COM!$N$4 -> #REF! | P90: =#REF!*COM!$P$4 -> #REF! | Q90: =#REF!*COM!$P$4 -> #REF! | R90: =#REF!*COM!$R$4 -> #REF! | S90: =#REF!*COM!$R$4 -> #REF!
A91: 311 | B91: 34 | C91: 920 | D91: 70989 | E91: ВБ | F91: Образование для будущего (ВБ) (грант) ДФ | H91: =#REF!*COM!$H$4 -> #REF! | I91: =#REF!*COM!$H$4 -> #REF! | J91: =#REF!*COM!$J$4 -> #REF! | K91: =#REF!*COM!$J$4 -> #REF! | L91: =#REF!*COM!$L$4 -> #REF! | M91: =#REF!*COM!$L$4 -> #REF! | N91: =#REF!*COM!$N$4 -> #REF! | O91: =#REF!*COM!$N$4 -> #REF! | P91: =#REF!*COM!$P$4 -> #REF! | Q91: =#REF!*COM!$P$4 -> #REF! | R91: =#REF!*COM!$R$4 -> #REF! | S91: =#REF!*COM!$R$4 -> #REF! | T91: =I91+K91+M91+O91+Q91+S91 -> #REF!
T93: =I93+K93+M93+O93+Q93+S93 -> 0
T94: =I94+K94+M94+O94+Q94+S94 -> 0
F95: Министерство здравоохранения КР | H95: =H96 -> #REF! | I95: =I96 -> #REF! | J95: =J96 -> #REF! | K95: =K96 -> #REF! | L95: =L96 -> #REF! | M95: =M96 -> #REF! | N95: =N96 -> #REF! | O95: =O96 -> #REF! | ... S95: =S96 -> #REF! | T95: =I95+K95+M95+O95+Q95+S95 -> #REF!
F96: Государственные инвестиции | H96: =SUM(H97:H126) -> #REF! | I96: =SUM(I97:I126) -> #REF! | J96: =SUM(J97:J126) -> #REF! | K96: =SUM(K97:K126) -> #REF! | L96: =SUM(L97:L126) -> #REF! | M96: =SUM(M97:M126) -> #REF! | N96: =SUM(N97:N126) -> #REF! | O96: =SUM(O97:O126) -> #REF! | ... S96: =SUM(S97:S126) -> #REF! | T96: =I96+K96+M96+O96+Q96+S96 -> #REF!
A97: 311 | B97: 37 | C97: 920 | D97: 70769 | E97: КфВ | F97: Создание национальной системы экстренной медицины (КфВ) - 1 (грант) | H97: =#REF!*COM!$H$4 -> #REF! | I97: =#REF!*COM!$H$4 -> #REF! | J97: =#REF!*COM!$J$4 -> #REF! | K97: =#REF!*COM!$J$4 -> #REF! | L97: =#REF!*COM!$L$4 -> #REF! | M97: =#REF!*COM!$L$4 -> #REF! | N97: =#REF!*COM!$N$4 -> #REF! | O97: =#REF!*COM!$N$4 -> #REF! | P97: =#REF!*COM!$P$4 -> #REF! | Q97: =#REF!*COM!$P$4 -> #REF! | R97: =#REF!*COM!$R$4 -> #REF! | S97: =#REF!*COM!$R$4 -> #REF! | T97: =I97+K97+M97+O97+Q97+S97 -> #REF!
A98: 311 | B98: 37 | C98: 910 | D98: 70769 | F98: Создание национальной системы экстренной медицины (КфВ) | H98: =#REF!*COM!$H$4 -> #REF! | I98: =#REF!*COM!$H$4 -> #REF! | J98: =#REF!*COM!$J$4 -> #REF! | K98: =#REF!*COM!$J$4 -> #REF! | L98: =#REF!*COM!$L$4 -> #REF! | M98: =#REF!*COM!$L$4 -> #REF! | N98: =#REF!*COM!$N$4 -> #REF! | O98: =#REF!*COM!$N$4 -> #REF! | P98: =#REF!*COM!$P$4 -> #REF! | Q98: =#REF!*COM!$P$4 -> #REF! | R98: =#REF!*COM!$R$4 -> #REF! | S98: =#REF!*COM!$R$4 -> #REF! | T98: =I98+K98+M98+O98+Q98+S98 -> #REF!
A99: 311 | B99: 37 | C99: 920 | D99: 70769 | E99: КфВ | F99: Проект «Здравоохранение и социальная защита» - 3, 4 (КфВ) (грант) | G99: BMZ ID: 2011 70 190/2013 70 030/2015 70 084 | H99: =#REF!*COM!$H$4 -> #REF! | I99: =#REF!*COM!$H$4 -> #REF! | J99: =#REF!*COM!$J$4 -> #REF! | K99: =#REF!*COM!$J$4 -> #REF! | L99: =#REF!*COM!$L$4 -> #REF! | M99: =#REF!*COM!$L$4 -> #REF! | N99: =#REF!*COM!$N$4 -> #REF! | O99: =#REF!*COM!$N$4 -> #REF! | P99: =#REF!*COM!$P$4 -> #REF! | Q99: =#REF!*COM!$P$4 -> #REF! | R99: =#REF!*COM!$R$4 -> #REF! | S99: =#REF!*COM!$R$4 -> #REF! | T99: =I99+K99+M99+O99+Q99+S99 -> #REF!
A100: 311 | B100: 37 | C100: 910 | D100: 70769 | F100: Борьба с туберкулезом-V (КфВ) | H100: =#REF!*COM!$H$4 -> #REF! | I100: =#REF!*COM!$H$4 -> #REF! | J100: =#REF!*COM!$J$4 -> #REF! | K100: =#REF!*COM!$J$4 -> #REF! | L100: =#REF!*COM!$L$4 -> #REF! | M100: =#REF!*COM!$L$4 -> #REF! | N100: =#REF!*COM!$N$4 -> #REF! | O100: =#REF!*COM!$N$4 -> #REF! | P100: =#REF!*COM!$P$4 -> #REF! | Q100: =#REF!*COM!$P$4 -> #REF! | R100: =#REF!*COM!$R$4 -> #REF! | S100: =#REF!*COM!$R$4 -> #REF! | T100: =I100+K100+M100+O100+Q100+S100 -> #REF!
A101: 311 | B101: 37 | C101: 920 | D101: 70769 | E101: КфВ | F101: Борьба с туберкулезом-V (КфВ) (грант) | H101: =#REF!*COM!$H$4 -> #REF! | I101: =#REF!*COM!$H$4 -> #REF! | J101: =#REF!*COM!$J$4 -> #REF! | K101: =#REF!*COM!$J$4 -> #REF! | L101: =#REF!*COM!$L$4 -> #REF! | M101: =#REF!*COM!$L$4 -> #REF! | N101: =#REF!*COM!$N$4 -> #REF! | O101: =#REF!*COM!$N$4 -> #REF! | P101: =#REF!*COM!$P$4 -> #REF! | Q101: =#REF!*COM!$P$4 -> #REF! | R101: =#REF!*COM!$R$4 -> #REF! | S101: =#REF!*COM!$R$4 -> #REF! | T101: =I101+K101+M101+O101+Q101+S101 -> #REF!
A102: 311 | B102: 37 | C102: 910 | D102: 70769 | F102: Охрана материнства и детства IV-V (КфВ) | H102: =#REF!*COM!$H$4 -> #REF! | I102: =#REF!*COM!$H$4 -> #REF! | J102: =#REF!*COM!$J$4 -> #REF! | K102: =#REF!*COM!$J$4 -> #REF! | L102: =#REF!*COM!$L$4 -> #REF! | M102: =#REF!*COM!$L$4 -> #REF! | N102: =#REF!*COM!$N$4 -> #REF! | O102: =#REF!*COM!$N$4 -> #REF! | P102: =#REF!*COM!$P$4 -> #REF! | Q102: =#REF!*COM!$P$4 -> #REF! | R102: =#REF!*COM!$R$4 -> #REF! | S102: =#REF!*COM!$R$4 -> #REF! | T102: =I102+K102+M102+O102+Q102+S102 -> #REF!
A103: 311 | B103: 37 | C103: 920 | D103: 70769 | E103: КфВ | F103: Охрана материнства и детства IV-V (КфВ) (грант) | G103: BMZ ID: 2007 66 543/2007 70 388/2009 66 622/2009 70 301 | H103: =#REF!*COM!$H$4 -> #REF! | I103: =#REF!*COM!$H$4 -> #REF! | J103: =#REF!*COM!$J$4 -> #REF! | K103: =#REF!*COM!$J$4 -> #REF! | L103: =#REF!*COM!$L$4 -> #REF! | M103: =#REF!*COM!$L$4 -> #REF! | N103: =#REF!*COM!$N$4 -> #REF! | O103: =#REF!*COM!$N$4 -> #REF! | P103: =#REF!*COM!$P$4 -> #REF! | Q103: =#REF!*COM!$P$4 -> #REF! | R103: =#REF!*COM!$R$4 -> #REF! | S103: =#REF!*COM!$R$4 -> #REF! | T103: =I103+K103+M103+O103+Q103+S103 -> #REF!
A104: 311 | B104: 37 | C104: 930 | D104: 70769 | E104: СФР | F104: Строительство нового корпуса для Городской детской клинической больницы скорой медицинской помощи города Бишкек (СФР) (кредит) | G104: 4/697 | H104: =#REF!*COM!$H$4 -> #REF! | I104: =#REF!*COM!$H$4 -> #REF! | J104: =#REF!*COM!$J$4 -> #REF! | K104: =#REF!*COM!$J$4 -> #REF! | L104: =#REF!*COM!$L$4 -> #REF! | M104: =#REF!*COM!$L$4 -> #REF! | N104: =#REF!*COM!$N$4 -> #REF! | O104: =#REF!*COM!$N$4 -> #REF! | P104: =#REF!*COM!$P$4 -> #REF! | Q104: =#REF!*COM!$P$4 -> #REF! | R104: =#REF!*COM!$R$4 -> #REF! | S104: =#REF!*COM!$R$4 -> #REF! | T104: =I104+K104+M104+O104+Q104+S104 -> #REF!
A105: 311 | B105: 37 | C105: 910 | D105: 70769 | F105: Строительство и оснащение нейрохирургического центра Национального госпиталя (КФАЭР) | H105: =#REF!*COM!$H$4 -> #REF! | I105: =#REF!*COM!$H$4 -> #REF! | J105: =#REF!*COM!$J$4 -> #REF! | K105: =#REF!*COM!$J$4 -> #REF! | L105: =#REF!*COM!$L$4 -> #REF! | M105: =#REF!*COM!$L$4 -> #REF! | N105: =#REF!*COM!$N$4 -> #REF! | O105: =#REF!*COM!$N$4 -> #REF! | P105: =#REF!*COM!$P$4 -> #REF! | Q105: =#REF!*COM!$P$4 -> #REF! | R105: =#REF!*COM!$R$4 -> #REF! | S105: =#REF!*COM!$R$4 -> #REF! | T105: =I105+K105+M105+O105+Q105+S105 -> #REF!
A106: 311 | B106: 37 | C106: 930 | D106: 70769 | E106: КФАЭР | F106: Строительство и оснащение нейрохирургического центра Национального госпиталя (КФАЭР) (кредит) | H106: =#REF!*COM!$H$4 -> #REF! | I106: =#REF!*COM!$H$4 -> #REF! | J106: =#REF!*COM!$J$4 -> #REF! | K106: =#REF!*COM!$J$4 -> #REF! | L106: =#REF!*COM!$L$4 -> #REF! | M106: =#REF!*COM!$L$4 -> #REF! | N106: =#REF!*COM!$N$4 -> #REF! | O106: =#REF!*COM!$N$4 -> #REF! | P106: =#REF!*COM!$P$4 -> #REF! | Q106: =#REF!*COM!$P$4 -> #REF! | R106: =#REF!*COM!$R$4 -> #REF! | S106: =#REF!*COM!$R$4 -> #REF! | T106: =I106+K106+M106+O106+Q106+S106 -> #REF!
A107: 311 | B107: 37 | C107: 920 | D107: 70769 | E107: КфВ | F107: Программа «Охрана материнства и детства» фаза VI-VIII г.Ош (КфВ) (грант) | G107: BMZID:2011 66 453/2012 67 368/2013 65 451/2013 70 022 | H107: =#REF!*COM!$H$4 -> #REF! | I107: =#REF!*COM!$H$4 -> #REF! | J107: =#REF!*COM!$J$4 -> #REF! | K107: =#REF!*COM!$J$4 -> #REF! | L107: =#REF!*COM!$L$4 -> #REF! | M107: =#REF!*COM!$L$4 -> #REF! | N107: =#REF!*COM!$N$4 -> #REF! | O107: =#REF!*COM!$N$4 -> #REF! | P107: =#REF!*COM!$P$4 -> #REF! | Q107: =#REF!*COM!$P$4 -> #REF! | R107: =#REF!*COM!$R$4 -> #REF! | S107: =#REF!*COM!$R$4 -> #REF! | T107: =I107+K107+M107+O107+Q107+S107 -> #REF!
A108: 311 | B108: 37 | C108: 920 | D108: 70769 | E108: КфВ | F108: Программа «Охрана материнства и детства» фаза IХ г.Талас (КфВ) (грант) | G108: BMZ ID:2013 67 275/2013 67 283 | H108: =#REF!*COM!$H$4 -> #REF! | I108: =#REF!*COM!$H$4 -> #REF! | J108: =#REF!*COM!$J$4 -> #REF! | K108: =#REF!*COM!$J$4 -> #REF! | L108: =#REF!*COM!$L$4 -> #REF! | M108: =#REF!*COM!$L$4 -> #REF! | N108: =#REF!*COM!$N$4 -> #REF! | O108: =#REF!*COM!$N$4 -> #REF! | P108: =#REF!*COM!$P$4 -> #REF! | Q108: =#REF!*COM!$P$4 -> #REF! | R108: =#REF!*COM!$R$4 -> #REF! | S108: =#REF!*COM!$R$4 -> #REF! | T108: =I108+K108+M108+O108+Q108+S108 -> #REF!
...

Sheet СОМ (без формул)
H4: 91.6 | J4: 88.4 | L4: 89.3 | N4: 89.5 | P4: 90 | R4: 90.5
A5: Классификация | E5: донор | F5: Наименование проекта | G5: номер и дата кредитного соглашения | H5: 2025 | J5: 2026 | L5: 2027 | N5: 2028 | P5: 2029 | R5: 2030
A6: III | B6: IV | D6: V | H6: Внутреннее | I6: Внешнее | J6: Внутреннее | K6: Внешнее | L6: Внутреннее | M6: Внешнее | N6: Внутреннее | O6: Внешнее | P6: Внутреннее | Q6: Внешнее | R6: Внутреннее | S6: Внешнее
F7: Министерство финансов КР | H7: 0 | I7: 1106656.2 | J7: 243.1 | K7: 2252456.8 | L7: 3238.911 | M7: 2318887.9 | N7: 0 | O7: 1249038.7 | P7: 0 | Q7: 1453217.4 | R7: 0 | S7: 1039845 | T7: 9420102
F8: Государственные инвестиции | H8: 0 | I8: 1106656.2 | J8: 243.1 | K8: 2252456.8 | L8: 3238.911 | M8: 2318887.9 | N8: 0 | O8: 1249038.7 | P8: 0 | Q8: 1453217.4 | R8: 0 | S8: 1039845 | T8: 9420102
A9: 311 | B9: 25 | C9: 910 | D9: 70499 | F9: Цепочка добавленной стоимости агрофинансирования (КфВ) Фаза 2 | H9: 0 | I9: 0 | J9: 243.1 | K9: 0 | L9: 245.6 | M9: 0 | N9: 0 | O9: 0 | P9: 0 | Q9: 0 | R9: 0 | S9: 0 | T9: 0
A10: 311 | B10: 25 | C10: 920 | D10: 70499 | E10: КфВ | F10: Цепочка добавленной стоимости агрофинансирования (КфВ) (грант) Фаза 2 | H10: 0 | I10: 0 | J10: 0 | K10: 551000.7 | L10: 0 | M10: 425650.2 | N10: 0 | O10: 0 | P10: 0 | Q10: 0 | R10: 0 | S10: 0 | T10: 976650.97
A11: 311 | B11: 25 | C11: 910 | D11: 70499 | F11: Цепочка добавленной стоимости агрофинансирования-2 (ИФЦА) | H11: 0 | I11: 0 | J11: 0 | K11: 0 | L11: 2993.3 | M11: 0 | N11: 0 | O11: 0 | P11: 0 | Q11: 0 | R11: 0 | S11: 0 | T11: 0
A12: 311 | B12: 25 | C12: 920 | D12: 70499 | E12: ИФЦА | F12: Цепочка добавленной стоимости агрофинансирования-2 (ИФЦА) (грант) | H12: 0 | I12: 0 | J12: 0 | K12: 63875.2 | L12: 0 | M12: 227281 | N12: 0 | O12: 0 | P12: 0 | Q12: 0 | R12: 0 | S12: 0 | T12: 291156.19
A13: 321 | B13: 25 | C13: 930 | D13: 70499 | E13: ЕИБ | F13: Цепочка добавленной стоимости агрофинансирования-2 (ЕИБ) (кредит) | G13: FI № 84.373 | H13: 0 | I13: 0 | J13: 0 | K13: 486200 | L13: 0 | M13: 598310 | N13: 0 | O13: 179000 | P13: 0 | Q13: 450000 | R13: 0 | S13: 452500 | T13: 2166010
A14: 311 | B14: 25 | C14: 920 | D14: 70499 | E14: ВБ | F14: Комплексное повышение производительности молочного сектора (ВБ) (грант) Доп. Финансирование | H14: 0 | I14: 4251.2 | J14: 0 | K14: 0 | L14: 0 | M14: 0 | N14: 0 | O14: 0 | P14: 0 | Q14: 0 | R14: 0 | S14: 0 | T14: 4251.156
A15: 321 | B15: 25 | C15: 920 | D15: 70499 | E15: ВБ | F15: Комплексное повышение производительности молочного сектора (ВБ) (грант) Доп. Финансирование | H15: 0 | I15: 0 | J15: 0 | K15: 0 | L15: 0 | M15: 0 | N15: 0 | O15: 0 | P15: 0 | Q15: 0 | R15: 0 | S15: 0 | T15: 0
A16: 311 | B16: 25 | C16: 930 | D16: 70499 | E16: ВБ | F16: Комплексное повышение производительности молочного сектора (ВБ) (кредит) Доп. Финансирование | G16: № 6941-KG | H16: 0 | I16: 16179.3 | J16: 0 | K16: 0 | L16: 0 | M16: 0 | N16: 0 | O16: 0 | P16: 0 | Q16: 0 | R16: 0 | S16: 0 | T16: 16179.308
A17: 321 | B17: 25 | C17: 930 | D17: 70499 | E17: ВБ | F17: Комплексное повышение производительности молочного сектора (ВБ) (кредит) Доп. Финансирование | H17: 0 | I17: 333292.1 | J17: 0 | K17: 103251.2 | L17: 0 | M17: 0 | N17: 0 | O17: 0 | P17: 0 | Q17: 0 | R17: 0 | S17: 0 | T17: 436543.3
A18: 311 | B18: 25 | C18: 920 | D18: 70499 | E18: ВБ | F18: Проект по поддержке частного сектора (ВБ) (грант) | H18: 0 | I18: 0 | J18: 0 | K18: 0 | L18: 0 | M18: 0 | N18: 0 | O18: 0 | P18: 0 | Q18: 0 | R18: 0 | S18: 0 | T18: 0
A19: 321 | B19: 25 | C19: 920 | D19: 70499 | E19: ВБ | F19: Проект по поддержке частного сектора (ВБ) (грант) | H19: 0 | I19: 0 | J19: 0 | K19: 0 | L19: 0 | M19: 0 | N19: 0 | O19: 0 | P19: 0 | Q19: 0 | R19: 0 | S19: 0 | T19: 0
A20: 321 | B20: 25 | C20: 930 | D20: 70499 | E20: ВБ | F20: Проект по поддержке частного сектора (ВБ) (кредит) | G20: № 6758-KG | H20: 0 | I20: 0 | J20: 0 | K20: 0 | L20: 0 | M20: 0 | N20: 0 | O20: 0 | P20: 0 | Q20: 0 | R20: 0 | S20: 0 | T20: 0
A21: 311 | B21: 25 | C21: 930 | D21: 70499 | E21: АБИИ | F21: Проект по поддержке частного сектора (АБИИ) (кредит) | G21: № 0423-А | H21: 0 | I21: 2851.5 | J21: 0 | K21: 0 | L21: 0 | M21: 0 | N21: 0 | O21: 0 | P21: 0 | Q21: 0 | R21: 0 | S21: 0 | T21: 2851.508
A22: 321 | B22: 25 | C22: 930 | D22: 70499 | E22: АБИИ | F22: Проект по поддержке частного сектора (АБИИ) (кредит) | H22: 0 | I22: 731762.2 | J22: 0 | K22: 0 | L22: 0 | M22: 0 | N22: 0 | O22: 0 | P22: 0 | Q22: 0 | R22: 0 | S22: 0 | T22: 731762.17
A23: 311 | B23: 25 | C23: 920 | D23: 70499 | E23: ВБ | F23: Экстренная поддержка микро, малых и средних предприятий ДФ (ВБ) (грант) | H23: 0 | I23: 0 | J23: 0 | K23: 0 | L23: 0 | M23: 0 | N23: 0 | O23: 0 | P23: 0 | Q23: 0 | R23: 0 | S23: 0 | T23: 0
A24: 321 | B24: 25 | C24: 920 | D24: 70499 | E24: ВБ | F24: Экстренная поддержка микро, малых и средних предприятий ДФ (ВБ) (грант) | H24: 0 | I24: 0 | J24: 0 | K24: 0 | L24: 0 | M24: 0 | N24: 0 | O24: 0 | P24: 0 | Q24: 0 | R24: 0 | S24: 0 | T24: 0
A25: 321 | B25: 25 | C25: 930 | D25: 70499 | E25: ВБ | F25: Экстренная поддержка микро, малых и средних предприятий ДФ (ВБ) (кредит) | G25: № 7094-KG | H25: 0 | I25: 0 | J25: 0 | K25: 0 | L25: 0 | M25: 0 | N25: 0 | O25: 0 | P25: 0 | Q25: 0 | R25: 0 | S25: 0 | T25: 0
A26: 311 | B26: 25 | C26: 930 | D26: 70499 | E26: ВБ | F26: Улучшение качества воздуха в городе Бишкек (ВБ) (кредит) | G26: № 7434-KG | H26: 0 | I26: 0 | J26: 0 | K26: 4420 | L26: 0 | M26: 13395 | N26: 0 | O26: 13425 | P26: 0 | Q26: 13500 | R26: 0 | S26: 13575 | T26: 58315
A27: 321 | B27: 25 | C27: 930 | D27: 70499 | E27: ВБ | F27: Улучшение качества воздуха в городе Бишкек (ВБ) (кредит) | H27: 0 | I27: 0 | J27: 0 | K27: 542776 | L27: 0 | M27: 548302 | N27: 0 | O27: 549530 | P27: 0 | Q27: 552600 | R27: 0 | S27: 573770 | T27: 2766978
A28: 311 | B28: 25 | C28: 930 | D28: 70499 | E28: ВБ | F28: Проект развития устойчивых агропродовольственных кластеров (ВБ) (кредит) | G28: № 7526-KG | H28: 0 | I28: 0 | J28: 0 | K28: 12965.6 | L28: 0 | M28: 13013.7 | N28: 0 | O28: 13043.7 | P28: 0 | Q28: 19517.4 | R28: 0 | S28: 0 | T28: 58540.447
A29: 321 | B29: 25 | C29: 930 | D29: 70499 | E29: ВБ | F29: Проект развития устойчивых агропродовольственных кластеров (ВБ) (кредит) | H29: 0 | I29: 0 | J29: 0 | K29: 487968 | L29: 0 | M29: 492936 | N29: 0 | O29: 494040 | P29: 0 | Q29: 417600 | R29: 0 | S29: 0 | T29: 1892544
A30: 311 | B30: 25 | C30: 930 | D30: 70499 | E30: ВБ | F30: Развитие устойчивых финансовых рынков для микро-, малых и средних предприятий в Кыргызской Республике (ВБ) (кредит) (план) | G30: 7741-KG | H30: 0 | I30: 0 | J30: 0 | K30: 0 | L30: 0 | M30: 0 | N30: 0 | O30: 0 | P30: 0 | Q30: 0 | R30: 0 | S30: 0 | T30: 0
A31: 321 | B31: 25 | C31: 930 | D31: 70499 | E31: ВБ | F31: Развитие устойчивых финансовых рынков для микро-, малых и средних предприятий в Кыргызской Республике (ВБ) (кредит) (план) | H31: 0 | I31: 0 | J31: 0 | K31: 0 | L31: 0 | M31: 0 | N31: 0 | O31: 0 | P31: 0 | Q31: 0 | R31: 0 | S31: 0 | T31: 0
A32: 311 | B32: 25 | C32: 920 | D32: 70499 | E32: ВБ | F32: Проект сельских инвестиций - 3 ДФ (ВБ) (грант) | H32: 0 | I32: 0 | J32: 0 | K32: 0 | L32: 0 | M32: 0 | N32: 0 | O32: 0 | P32: 0 | Q32: 0 | R32: 0 | S32: 0
A33: 311 | B33: 25 | C33: 930 | D33: 70499 | E33: ВБ | F33: Проект сельских инвестиций - 3 ДФ (ВБ) (кредит) | H33: 0 | I33: 18320 | J33: 0 | K33: 0 | L33: 0 | M33: 0 | N33: 0 | O33: 0 | P33: 0 | Q33: 0 | R33: 0 | S33: 0
T34: 0
T36: 0
T37: 0
T38: 0
F39: Министерство экономики и коммерции КР | H39: 0 | I39: 5596760 | J39: 0 | K39: 4345551.3 | L39: 0 | M39: 3799801.6 | N39: 0 | O39: 7481928.8 | P39: 0 | Q39: 2764350 | R39: 0 | S39: 1577867.5 | T39: 25566259
F40: Государственные инвестиции | H40: 0 | I40: 5596760 | J40: 0 | K40: 4345551.3 | L40: 0 | M40: 3799801.6 | N40: 0 | O40: 7481928.8 | P40: 0 | Q40: 2764350 | R40: 0 | S40: 1577867.5 | T40: 25566259
A41: 311 | B41: 28 | C41: 920 | D41: 70499 | E41: ВБ | F41: Проект регионального экономического развития Ошской области (ВБ) (грант) | G41: Грант D5700-KG/Кредит 6558-KG | H41: 0 | I41: 916000 | J41: 0 | K41: 0 | L41: 0 | M41: 23276.045 | N41: 0 | O41: 0 | P41: 0 | Q41: 0 | R41: 0 | S41: 0 | T41: 939276.05
A42: 311 | B42: 28 | C42: 930 | D42: 70499 | E42: ВБ | F42: Проект регионального экономического развития Ошской области (ВБ) (кредит) | H42: 0 | I42: 732800 | J42: 0 | K42: 1591200 | L42: 0 | M42: 357200 | N42: 0 | O42: 0 | P42: 0 | Q42: 0 | R42: 0 | S42: 0 | T42: 2681200
A43: 311 | B43: 28 | C43: 930 | D43: 70499 | E43: ВБ | F43: Проект регионального экономического развития Ошской области - дополнительное финансирование (ВБ) (кредит) | H43: 0 | I43: 0 | J43: 0 | K43: 88400 | L43: 0 | M43: 267900 | N43: 0 | O43: 358000 | P43: 0 | Q43: 45000 | R43: 0 | S43: 0 | T43: 759300
A44: 311 | B44: 28 | C44: 920 | D44: 70499 | E44: ВБ | F44: Проект регионального экономического развития Баткенской области (ВБ) (грант) | G44: Грант D976-KG/Кредит 70490-KG | H44: 0 | I44: 732800 | J44: 0 | K44: 751400 | L44: 0 | M44: 491150 | N44: 0 | O44: 25346.4 | P44: 0 | Q44: 0 | R44: 0 | S44: 0 | T44: 2000696.4
A45: 311 | B45: 28 | C45: 930 | D45: 70499 | E45: ВБ | F45: Проект регионального экономического развития Баткенской области (ВБ) (кредит) | H45: 0 | I45: 366400 | J45: 0 | K45: 353600 | L45: 0 | M45: 357200 | N45: 0 | O45: 156038.77 | P45: 0 | Q45: 90000 | R45: 0 | S45: 181000 | T45: 1504238.8
A46: 311 | B46: 28 | C46: 920 | D46: 70499 | E46: ВБ | F46: Национальный проект по инициативе сообществ (ВБ) (грант) | G46: Грант D976-KG, Кредит 7049-KG | H46: 0 | I46: 18320 | J46: 0 | K46: 17680 | L46: 0 | M46: 142880 | N46: 0 | O46: 0 | P46: 0 | Q46: 0 | R46: 0 | S46: 0 | T46: 178880
A47: 311 | B47: 28 | C47: 930 | D47: 70499 | E47: ВБ | F47: Национальный проект по инициативе сообществ (ВБ) (кредит) | H47: 0 | I47: 73280 | J47: 0 | K47: 159120 | L47: 0 | M47: 446500 | N47: 0 | O47: 1074000 | P47: 0 | Q47: 486000 | R47: 0 | S47: 0 | T47: 2238900
A48: 311 | B48: 28 | C48: 910 | D48: 70499 | F48: Деятельность «Развитие центра бизнес-услуг», SEFF 2 (АБР) (план) | H48: 0 | I48: 0 | J48: 0 | K48: 0 | L48: 0 | M48: 0 | N48: 0 | O48: 0 | P48: 0 | Q48: 0 | R48: 0 | S48: 0
A49: 311 | B49: 28 | C49: 920 | D49: 70499 | E49: АБР | F49: Деятельность «Развитие центра бизнес-услуг», SEFF 2 (АБР) (грант) (план) | H49: 0 | I49: 0 | J49: 0 | K49: 0 | L49: 0 | M49: 0 | N49: 0 | O49: 0 | P49: 0 | Q49: 0 | R49: 0 | S49: 0
A50: 311 | B50: 28 | C50: 910 | D50: 70499 | F50: Энергоэффективность в общественных зданиях (АБР) (план) | H50: 0 | I50: 0 | J50: 0 | K50: 0 | L50: 0 | M50: 0 | N50: 0 | O50: 0 | P50: 0 | Q50: 0 | R50: 0 | S50: 0
A51: 311 | B51: 28 | C51: 920 | D51: 70499 | E51: АБР | F51: Энергоэффективность в общественных зданиях (АБР) (грант) (план) | H51: 0 | I51: 0 | J51: 0 | K51: 0 | L51: 0 | M51: 0 | N51: 0 | O51: 0 | P51: 0 | Q51: 0 | R51: 0 | S51: 0
A52: 311 | B52: 28 | C52: 930 | D52: 70499 | E52: АБР | F52: Энергоэффективность в общественных зданиях (АБР) (кредит) (план) | H52: 0 | I52: 0 | J52: 0 | K52: 0 | L52: 0 | M52: 0 | N52: 0 | O52: 0 | P52: 0 | Q52: 0 | R52: 0 | S52: 0
A53: 311 | B53: 28 | C53: 920 | D53: 70499 | E53: КфВ | F53: Программа жилищного финансирования (КфВ) (грант) | H53: 0 | I53: 0 | J53: 0 | K53: 2073.9 | L53: 0 | M53: 0 | N53: 0 | O53: 0 | P53: 0 | Q53: 0 | R53: 0 | S53: 0 | T53: 2073.864
A54: 311 | B54: 28 | C54: 920 | D54: 70499 | E54: КфВ | F54: Программа жилищного финансирования (КфВ) (грант) Фаза 2 (план) | H54: 0 | I54: 9160 | J54: 0 | K54: 11877.424 | L54: 0 | M54: 14093.326 | N54: 0 | O54: 14124.89 | P54: 0 | Q54: 0 | R54: 0 | S54: 0 | T54: 49255.64
A55: 311 | B55: 28 | C55: 910 | D55: 70499 | F55: Строительство многоэтажных социальных жилых домов (СФР) | H55: 0 | I55: 0 | J55: 0 | K55: 0 | L55: 0 | M55: 0 | N55: 0 | O55: 0 | P55: 0 | Q55: 0 | R55: 0 | S55: 0
A56: 321 | B56: 28 | C56: 930 | D56: 70499 | E56: СФР | F56: Строительство многоэтажных социальных жилых домов (СФР) (кредит) | G56: 09/789 | H56: 0 | I56: 1832000 | J56: 0 | K56: 1326000 | L56: 0 | M56: 1339500 | N56: 0 | O56: 2808510 | P56: 0 | Q56: 1204200 | R56: 0 | S56: 452500 | T56: 8962710
A57: 311 | B57: 28 | C57: 910 | D57: 70499 | F57: Финансирование доступного жилья по стандартам шариата (ИБР) | H57: 0 | I57: 0 | J57: 0 | K57: 0 | L57: 0 | M57: 0 | N57: 0 | O57: 0 | P57: 0 | Q57: 0 | R57: 0 | S57: 0
A58: 311 | B58: 28 | C58: 930 | D58: 70499 | E58: ИБР | F58: Финансирование доступного жилья по стандартам шариата (ИБР) (кредит) | G58: KGZ-1028 | H58: 0 | I58: 0 | J58: 0 | K58: 0 | L58: 0 | M58: 0 | N58: 0 | O58: 0 | P58: 0 | Q58: 0 | R58: 0 | S58: 0 | T58: 0
A59: 321 | B59: 28 | C59: 930 | D59: 70499 | E59: ИБР | F59: Финансирование доступного жилья по стандартам шариата (ИБР) (кредит) | H59: 0 | I59: 916000 | J59: 0 | K59: 44200 | L59: 0 | M59: 360102.25 | N59: 0 | O59: 3045908.8 | P59: 0 | Q59: 939150 | R59: 0 | S59: 944367.5 | T59: 6249728.5
A60: 311 | B60: 28 | C60: 910 | D60: 70499 | F60: Расширение доступа к доступному и энергоэффективному жилью (АБР) (план) | H60: 0 | I60: 0 | J60: 0 | K60: 0 | L60: 0 | M60: 0 | N60: 0 | O60: 0 | P60: 0 | Q60: 0 | R60: 0 | S60: 0
A61: 321 | B61: 28 | C61: 920 | D61: 70499 | E61: АБР | F61: Расширение доступа к доступному и энергоэффективному жилью (АБР) (грант) (план) | H61: 0 | I61: 0 | J61: 0 | K61: 0 | L61: 0 | M61: 0 | N61: 0 | O61: 0 | P61: 0 | Q61: 0 | R61: 0 | S61: 0 | T61: 0
A62: 321 | B62: 28 | C62: 930 | D62: 70499 | E62: АБР | F62: Расширение доступа к доступному и энергоэффективному жилью (АБР) (кредит) (план) | H62: 0 | I62: 0 | J62: 0 | K62: 0 | L62: 0 | M62: 0 | N62: 0 | O62: 0 | P62: 0 | Q62: 0 | R62: 0 | S62: 0 | T62: 0
A63: 321 | B63: 28 | C63: 930 | D63: 70499 | E63: EDCF | F63: Строительство социального жилья (EDCF) (кредит) (план) | H63: 0 | I63: 0 | J63: 0 | K63: 0 | L63: 0 | M63: 0 | N63: 0 | O63: 0 | P63: 0 | Q63: 0 | R63: 0 | S63: 0
T67: 0
T68: 0
F69: Государственная налоговая служба при Министерстве финансов КР | H69: 0 | I69: 387330.6 | J69: 0 | K69: 165348.66 | L69: 0 | M69: 0 | N69: 0 | O69: 0 | P69: 0 | Q69: 0 | R69: 0 | S69: 0 | T69: 552679.26
F70: Государственные инвестиции | H70: 0 | I70: 387330.6 | J70: 0 | K70: 165348.66 | L70: 0 | M70: 0 | N70: 0 | O70: 0 | P70: 0 | Q70: 0 | R70: 0 | S70: 0 | T70: 552679.26
A71: 311 | B71: 25 | C71: 920 | D71: 70499 | E71: ВБ | F71: Модернизация системы налогового администрирования и статистической системы (ВБ) (грант) | H71: 0 | I71: 170641.64 | J71: 0 | K71: 165348.66 | L71: 0 | M71: 0 | N71: 0 | O71: 0 | P71: 0 | Q71: 0 | R71: 0 | S71: 0 | T71: 335990.3
A72: 311 | B72: 25 | C72: 930 | D72: 70499 | E72: ВБ | F72: Модернизация системы налогового администрирования и статистической системы (ВБ) (кредит) | G72: 6546-KG | H72: 0 | I72: 216688.96 | J72: 0 | K72: 0 | L72: 0 | M72: 0 | N72: 0 | O72: 0 | P72: 0 | Q72: 0 | R72: 0 | S72: 0 | T72: 216688.96
T73: 0
T74: 0
T75: 0
T76: 0
T77: 0
F78: Министерство образования и науки КР | H78: 0 | I78: 1232084.1 | J78: 88400 | K78: 923780 | L78: 89300 | M78: 1080530 | N78: 71600 | O78: 1543875 | P78: 0 | Q78: 828000 | R78: 0 | S78: 0 | T78: 5608269.1
F79: Государственные инвестиции | H79: 0 | I79: 1232084.1 | J79: 88400 | K79: 923780 | L79: 89300 | M79: 1080530 | N79: 71600 | O79: 1543875 | P79: 0 | Q79: 828000 | R79: 0 | S79: 0 | T79: 5608269.1
A80: 311 | B80: 34 | C80: 920 | D80: 70989 | E80: ВБ | F80: Образование для будущего (ВБ) (грант) | H80: 0 | I80: 569074.16 | J80: 0 | K80: 0 | L80: 0 | M80: 0 | N80: 0 | O80: 0 | P80: 0 | Q80: 0 | R80: 0 | S80: 0 | T80: 569074.16
A81: 311 | B81: 34 | C81: 930 | D81: 70989 | E81: ВБ | F81: Образование для будущего (ВБ) (кредит) | G81: 6563-KG | H81: 0 | I81: 569074.16 | J81: 0 | K81: 0 | L81: 0 | M81: 0 | N81: 0 | O81: 0 | P81: 0 | Q81: 0 | R81: 0 | S81: 0 | T81: 569074.16
A82: 311 | B82: 34 | C82: 920 | D82: 70989 | E82: ВБ | F82: Укрепление основ обучения (ВБ) (грант) | H82: 0 | I82: 93935.8 | J82: 0 | K82: 0 | L82: 0 | M82: 0 | N82: 0 | O82: 0 | P82: 0 | Q82: 0 | R82: 0 | S82: 0 | T82: 93935.8
A83: 311 | B83: 34 | C83: 910 | D83: 70989 | F83: Программа развития сектора: реформирование системы школьного образования (АБР) (план) | H83: 0 | I83: 0 | J83: 88400 | K83: 0 | L83: 89300 | M83: 0 | N83: 71600 | O83: 0 | P83: 0 | Q83: 0 | R83: 0 | S83: 0 | T83: 0
A84: 311 | B84: 34 | C84: 920 | D84: 70989 | E84: АБР | F84: Программа развития сектора: реформирование сектора школьного образования (АБР) (грант) (план) | G84: №0851 | H84: 0 | I84: 0 | J84: 0 | K84: 88400 | L84: 0 | M84: 160740 | N84: 0 | O84: 152150 | P84: 0 | Q84: 0 | R84: 0 | S84: 0 | T84: 401290
A85: 311 | B85: 34 | C85: 930 | D85: 70989 | E85: АБР | F85: Программа развития сектора: реформирование сектора школьного образования (АБР) (кредит) (план) | G85: №4217 | H85: 0 | I85: 0 | J85: 0 | K85: 424320 | L85: 0 | M85: 437570 | N85: 0 | O85: 698100 | P85: 0 | Q85: 180000 | R85: 0 | S85: 0 | T85: 1739990
A86: 311 | B86: 34 | C86: 930 | D86: 70989 | E86: ВБ | F86: Качество высшего образования и инновации (ВБ) (кредит) (план) | G86: 7480-KG | H86: 0 | I86: 0 | J86: 0 | K86: 411060 | L86: 0 | M86: 482220 | N86: 0 | O86: 693625 | P86: 0 | Q86: 648000 | R86: 0 | S86: 0 | T86: 2234905
A87: 311 | B87: 34 | C87: 920 | D87: 70989 | E87: ЕФСР | F87: Smart-Ed по улучшению доступа к возможностям инклюзивного обучения и его качества для всех детей в Кыргызской Республике» (ЕФСР) (грант) | H87: 0 | I87: 0 | J87: 0 | K87: 0 | L87: 0 | M87: 0 | N87: 0 | O87: 0 | P87: 0 | Q87: 0 | R87: 0 | S87: 0 | T87: 0
A88: 311 | B88: 34 | C88: 920 | D88: 70989 | E88: ИБР | F88: Smart-Ed по улучшению доступа к возможностям инклюзивного обучения и его качества для всех детей в Кыргызской Республике» (ИБР) (грант) | H88: 0 | I88: 0 | J88: 0 | K88: 0 | L88: 0 | M88: 0 | N88: 0 | O88: 0 | P88: 0 | Q88: 0 | R88: 0 | S88: 0
A89: 311 | B89: 34 | C89: 930 | D89: 70989 | E89: ИБР | F89: Smart-Ed по улучшению доступа к возможностям инклюзивного обучения и его качества для всех детей в Кыргызской Республике» (ИБР) (кредит) | H89: 0 | I89: 0 | J89: 0 | K89: 0 | L89: 0 | M89: 0 | N89: 0 | O89: 0 | P89: 0 | Q89: 0 | R89: 0 | S89: 0 | T89: 0
A90: 311 | B90: 34 | C90: 920 | D90: 70989 | E90: ГПЦО | F90: Smart-Ed по улучшению доступа к возможностям инклюзивного обучения и его качества для всех детей в Кыргызской Республике» | H90: 0 | I90: 0 | J90: 0 | K90: 0 | L90: 0 | M90: 0 | N90: 0 | O90: 0 | P90: 0 | Q90: 0 | R90: 0 | S90: 0
A91: 311 | B91: 34 | C91: 920 | D91: 70989 | E91: ВБ | F91: Образование для будущего (ВБ) (грант) ДФ | H91: 0 | I91: 0 | J91: 0 | K91: 0 | L91: 0 | M91: 0 | N91: 0 | O91: 0 | P91: 0 | Q91: 0 | R91: 0 | S91: 0 | T91: 0
T93: 0
T94: 0
F95: Министерство здравоохранения КР | H95: 0 | I95: 2638091.9 | J95: 85173.4 | K95: 2502849.8 | L95: 80370 | M95: 2218015.5 | N95: 13425 | O95: 906222.41 | P95: 0 | Q95: 956496.6 | R95: 0 | S95: 0 | T95: 9221676.2
F96: Государственные инвестиции | H96: 0 | I96: 2638091.9 | J96: 85173.4 | K96: 2502849.8 | L96: 80370 | M96: 2218015.5 | N96: 13425 | O96: 906222.41 | P96: 0 | Q96: 956496.6 | R96: 0 | S96: 0 | T96: 9221676.2
A97: 311 | B97: 37 | C97: 920 | D97: 70769 | E97: КфВ | F97: Создание национальной системы экстренной медицины (КфВ) - 1 (грант) | H97: 0 | I97: 0 | J97: 0 | K97: 0 | L97: 0 | M97: 0 | N97: 0 | O97: 0 | P97: 0 | Q97: 0 | R97: 0 | S97: 0 | T97: 0
A98: 311 | B98: 37 | C98: 910 | D98: 70769 | F98: Создание национальной системы экстренной медицины (КфВ) | H98: 0 | I98: 0 | J98: 0 | K98: 0 | L98: 0 | M98: 0 | N98: 0 | O98: 0 | P98: 0 | Q98: 0 | R98: 0 | S98: 0 | T98: 0
A99: 311 | B99: 37 | C99: 920 | D99: 70769 | E99: КфВ | F99: Проект «Здравоохранение и социальная защита» - 3, 4 (КфВ) (грант) | G99: BMZ ID: 2011 70 190/2013 70 030/2015 70 084 | H99: 0 | I99: 9867.152 | J99: 0 | K99: 3400.748 | L99: 0 | M99: 0 | N99: 0 | O99: 0 | P99: 0 | Q99: 0 | R99: 0 | S99: 0 | T99: 13267.9
A100: 311 | B100: 37 | C100: 910 | D100: 70769 | F100: Борьба с туберкулезом-V (КфВ) | H100: 0 | I100: 0 | J100: 0 | K100: 0 | L100: 0 | M100: 0 | N100: 0 | O100: 0 | P100: 0 | Q100: 0 | R100: 0 | S100: 0 | T100: 0
A101: 311 | B101: 37 | C101: 920 | D101: 70769 | E101: КфВ | F101: Борьба с туберкулезом-V (КфВ) (грант) | H101: 0 | I101: 0 | J101: 0 | K101: 0 | L101: 0 | M101: 0 | N101: 0 | O101: 0 | P101: 0 | Q101: 0 | R101: 0 | S101: 0 | T101: 0
A102: 311 | B102: 37 | C102: 910 | D102: 70769 | F102: Охрана материнства и детства IV-V (КфВ) | H102: 0 | I102: 0 | J102: 0 | K102: 0 | L102: 0 | M102: 0 | N102: 0 | O102: 0 | P102: 0 | Q102: 0 | R102: 0 | S102: 0 | T102: 0
A103: 311 | B103: 37 | C103: 920 | D103: 70769 | E103: КфВ | F103: Охрана материнства и детства IV-V (КфВ) (грант) | G103: BMZ ID: 2007 66 543/2007 70 388/2009 66 622/2009 70 301 | H103: 0 | I103: 24081.64 | J103: 0 | K103: 2278.068 | L103: 0 | M103: 0 | N103: 0 | O103: 0 | P103: 0 | Q103: 0 | R103: 0 | S103: 0 | T103: 26359.708
A104: 311 | B104: 37 | C104: 930 | D104: 70769 | E104: СФР | F104: Строительство нового корпуса для Городской детской клинической больницы скорой медицинской помощи города Бишкек (СФР) (кредит) | G104: 4/697 | H104: 0 | I104: 1158987.3 | J104: 0 | K104: 695975.85 | L104: 0 | M104: 0 | N104: 0 | O104: 0 | P104: 0 | Q104: 0 | R104: 0 | S104: 0 | T104: 1854963.2
A105: 311 | B105: 37 | C105: 910 | D105: 70769 | F105: Строительство и оснащение нейрохирургического центра Национального госпиталя (КФАЭР) | H105: 0 | I105: 0 | J105: 0 | K105: 0 | L105: 0 | M105: 0 | N105: 0 | O105: 0 | P105: 0 | Q105: 0 | R105: 0 | S105: 0 | T105: 0
A106: 311 | B106: 37 | C106: 930 | D106: 70769 | E106: КФАЭР | F106: Строительство и оснащение нейрохирургического центра Национального госпиталя (КФАЭР) (кредит) | H106: 0 | I106: 0 | J106: 0 | K106: 0 | L106: 0 | M106: 0 | N106: 0 | O106: 0 | P106: 0 | Q106: 0 | R106: 0 | S106: 0 | T106: 0
A107: 311 | B107: 37 | C107: 920 | D107: 70769 | E107: КфВ | F107: Программа «Охрана материнства и детства» фаза VI-VIII г.Ош (КфВ) (грант) | G107: BMZID:2011 66 453/2012 67 368/2013 65 451/2013 70 022 | H107: 0 | I107: 139758.7 | J107: 0 | K107: 217972.3 | L107: 0 | M107: 411137.2 | N107: 0 | O107: 347241.21 | P107: 0 | Q107: 0 | R107: 0 | S107: 0 | T107: 1116109.4
A108: 311 | B108: 37 | C108: 920 | D108: 70769 | E108: КфВ | F108: Программа «Охрана материнства и детства» фаза IХ г.Талас (КфВ) (грант) | G108: BMZ ID:2013 67 275/2013 67 283 | H108: 0 | I108: 130535.5 | J108: 0 | K108: 148075.3 | L108: 0 | M108: 202648.49 | N108: 0 | O108: 0 | P108: 0 | Q108: 0 | R108: 0 | S108: 0 | T108: 481259.29
...

Sheet Приложение 8
H1: Приложение 8 к Закону Кыргызской Республики «О республиканском бюджете Кыргызской Республики на 2026 год и плановый период 2027–2028 годов»
A3: Бюджет государственных инвестиций на 2026–2028 годы
F4: 88.4 | H4: 89.3 | J4: 89.5 | K4: (тыс. сом.)
A5: Классификация | E5: Наименование проекта | F5: 2026 год (проект) | H5: 2027 год (плановый период) | J5: 2028 год (плановый период)
A6: III | B6: IV | D6: V | F6: Внутреннее | G6: Внешнее | H6: Внутреннее | I6: Внешнее | J6: Внутреннее | K6: Внешнее
E7: Министерство финансов Кыргызской Республики | F7: 243.1 | G7: 2252456.7 | H7: 3238.9 | I7: 2318887.9 | J7: 0 | K7: 1249038.7
E8: Государственные инвестиции | F8: 243.1 | G8: 2252456.7 | H8: 3238.9 | I8: 2318887.9 | J8: 0 | K8: 1249038.7
A9: 311 | B9: 25 | C9: 910 | D9: 70499 | E9: Цепочка добавленной стоимости агрофинансирования (КфВ) Фаза 2 | F9: 243.1 | G9: 0 | H9: 245.6 | I9: 0 | J9: 0 | K9: 0
A10: 311 | B10: 25 | C10: 920 | D10: 70499 | E10: Цепочка добавленной стоимости агрофинансирования (КфВ) (грант) Фаза 2 | F10: 0 | G10: 551000.7 | H10: 0 | I10: 425650.2 | J10: 0 | K10: 0
A11: 311 | B11: 25 | C11: 910 | D11: 70499 | E11: Цепочка добавленной стоимости агрофинансирования-2 (ИФЦА) | F11: 0 | G11: 0 | H11: 2993.3 | I11: 0 | J11: 0 | K11: 0
A12: 311 | B12: 25 | C12: 920 | D12: 70499 | E12: Цепочка добавленной стоимости агрофинансирования-2 (ИФЦА) (грант) | F12: 0 | G12: 63875.2 | H12: 0 | I12: 227281 | J12: 0 | K12: 0
A13: 321 | B13: 25 | C13: 930 | D13: 70499 | E13: Цепочка добавленной стоимости агрофинансирования-2 (ЕИБ) (кредит) | F13: 0 | G13: 486200 | H13: 0 | I13: 598310 | J13: 0 | K13: 179000
A14: 311 | B14: 25 | C14: 920 | D14: 70499 | E14: Комплексное повышение производительности молочного сектора (ВБ) (грант) Доп. Финансирование | F14: 0 | G14: 0 | H14: 0 | I14: 0 | J14: 0 | K14: 0
A15: 321 | B15: 25 | C15: 920 | D15: 70499 | E15: Комплексное повышение производительности молочного сектора (ВБ) (грант) Доп. Финансирование | F15: 0 | G15: 0 | H15: 0 | I15: 0 | J15: 0 | K15: 0
A16: 311 | B16: 25 | C16: 930 | D16: 70499 | E16: Комплексное повышение производительности молочного сектора (ВБ) (кредит) Доп. Финансирование | F16: 0 | G16: 0 | H16: 0 | I16: 0 | J16: 0 | K16: 0
A17: 321 | B17: 25 | C17: 930 | D17: 70499 | E17: Комплексное повышение производительности молочного сектора (ВБ) (кредит) Доп. Финансирование | F17: 0 | G17: 103251.2 | H17: 0 | I17: 0 | J17: 0 | K17: 0
A18: 311 | B18: 25 | C18: 920 | D18: 70499 | E18: Проект по поддержке частного сектора (ВБ) (грант) | F18: 0 | G18: 0 | H18: 0 | I18: 0 | J18: 0 | K18: 0
A19: 321 | B19: 25 | C19: 920 | D19: 70499 | E19: Проект по поддержке частного сектора (ВБ) (грант) | F19: 0 | G19: 0 | H19: 0 | I19: 0 | J19: 0 | K19: 0
A20: 321 | B20: 25 | C20: 930 | D20: 70499 | E20: Проект по поддержке частного сектора (ВБ) (кредит) | F20: 0 | G20: 0 | H20: 0 | I20: 0 | J20: 0 | K20: 0
... A31: 321 | B31: 25 | C31: 930 | D31: 70499 | E31: Развитие устойчивых финансовых рынков для микро-, малых и средних предприятий в Кыргызской Республике (ВБ) (кредит) (план) | F31: 0 | G31: 0 | H31: 0 | I31: 0 | J31: 0 | K31: 0
A32: 311 | B32: 25 | C32: 930 | D32: 70499 | E32: Развитие устойчивых финансовых рынков для микро-, малых и средних предприятий в Кыргызской Республике (АБИИ) (кредит) (план)
A33: 321 | B33: 25 | C33: 930 | D33: 70499 | E33: Развитие устойчивых финансовых рынков для микро-, малых и средних предприятий в Кыргызской Республике (АБИИ) (кредит) (план)
E35: Министерство экономики и коммерции Кыргызской Республики | F35: 0 | G35: 4345551.3 | H35: 0 | I35: 3799801.6 | J35: 0 | K35: 7481928.9
E36: Государственные инвестиции | F36: 0 | G36: 4345551.3 | H36: 0 | I36: 3799801.6 | J36: 0 | K36: 7481928.9
A37: 311 | B37: 28 | C37: 920 | D37: 70499 | E37: Проект регионального экономического развития Ошской области (ВБ) (грант) | F37: 0 | G37: 0 | H37: 0 | I37: 23276 | J37: 0 | K37: 0
A38: 311 | B38: 28 | C38: 930 | D38: 70499 | E38: Проект регионального экономического развития Ошской области (ВБ) (кредит) | F38: 0 | G38: 1591200 | H38: 0 | I38: 357200 | J38: 0 | K38: 0
A39: 311 | B39: 28 | C39: 930 | D39: 70499 | E39: Проект регионального экономического развития Ошской области - дополнительное финансирование (ВБ) (кредит) | F39: 0 | G39: 88400 | H39: 0 | I39: 267900 | J39: 0 | K39: 358000
A40: 311 | B40: 28 | C40: 920 | D40: 70499 | E40: Проект регионального экономического развития Баткенской области (ВБ) (грант) | F40: 0 | G40: 751400 | H40: 0 | I40: 491150 | J40: 0 | K40: 25346.4
A41: 311 | B41: 28 | C41: 930 | D41: 70499 | E41: Проект регионального экономического развития Баткенской области (ВБ) (кредит) | F41: 0 | G41: 353600 | H41: 0 | I41: 357200 | J41: 0 | K41: 156038.8
A42: 311 | B42: 28 | C42: 920 | D42: 70499 | E42: Национальный проект по инициативе сообществ (ВБ) (грант) | F42: 0 | G42: 17680 | H42: 0 | I42: 142880 | J42: 0 | K42: 0
A43: 311 | B43: 28 | C43: 930 | D43: 70499 | E43: Национальный проект по инициативе сообществ (ВБ) (кредит) | F43: 0 | G43: 159120 | H43: 0 | I43: 446500 | J43: 0 | K43: 1074000
A44: 311 | B44: 28 | C44: 910 | D44: 70499 | E44: Деятельность «Развитие центра бизнес-услуг», SEFF 2 (АБР) (план) | F44: 0 | G44: 0 | H44: 0 | I44: 0 | J44: 0 | K44: 0
A45: 311 | B45: 28 | C45: 920 | D45: 70499 | E45: Деятельность «Развитие центра бизнес-услуг», SEFF 2 (АБР) (грант) (план) | F45: 0 | G45: 0 | H45: 0 | I45: 0 | J45: 0 | K45: 0
A46: 311 | B46: 28 | C46: 910 | D46: 70499 | E46: Программа зеленой трансформации общественных зданий (АБР) (план)
A47: 311 | B47: 28 | C47: 920 | D47: 70499 | E47: Программа зеленой трансформации общественных зданий (АБР) (грант) (план)
A48: 311 | B48: 28 | C48: 930 | D48: 70499 | E48: Программа зеленой трансформации общественных зданий (АБР) (кредит) (план)
A49: 311 | B49: 28 | C49: 920 | D49: 70499 | E49: Программа жилищного финансирования (КфВ) (грант) | F49: 0 | G49: 2073.9 | H49: 0 | I49: 0 | J49: 0 | K49: 0
A50: 311 | B50: 28 | C50: 920 | D50: 70499 | E50: Программа жилищного финансирования (КфВ) (грант) Фаза 2 (план) | F50: 0 | G50: 11877.4 | H50: 0 | I50: 14093.3 | J50: 0 | K50: 14124.9
A51: 311 | B51: 28 | C51: 910 | D51: 70499 | E51: Строительство многоэтажных социальных жилых домов (СФР) | F51: 0 | G51: 0 | H51: 0 | I51: 0 | J51: 0 | K51: 0
A52: 321 | B52: 28 | C52: 930 | D52: 70499 | E52: Строительство многоэтажных социальных жилых домов (СФР) (кредит) | F52: 0 | G52: 1326000 | H52: 0 | I52: 1339500 | J52: 0 | K52: 2808510
A53: 311 | B53: 28 | C53: 910 | D53: 70499 | E53: Финансирование доступного жилья по стандартам шариата (ИБР) | F53: 0 | G53: 0 | H53: 0 | I53: 0 | J53: 0 | K53: 0
A54: 311 | B54: 28 | C54: 930 | D54: 70499 | E54: Финансирование доступного жилья по стандартам шариата (ИБР) (кредит) | F54: 0 | G54: 0 | H54: 0 | I54: 0 | J54: 0 | K54: 0
A55: 321 | B55: 28 | C55: 930 | D55: 70499 | E55: Финансирование доступного жилья по стандартам шариата (ИБР) (кредит) | F55: 0 | G55: 44200 | H55: 0 | I55: 360102.3 | J55: 0 | K55: 3045908.8
A56: 321 | B56: 28 | C56: 930 | D56: 70499 | E56: Строительство социального жилья (EDCF) (кредит) (план) | F56: 0 | G56: 0 | H56: 0 | I56: 0 | J56: 0 | K56: 0
E58: Государственная налоговая служба при Министерстве финансов Кыргызской Республики | F58: 0 | G58: 165348.7 | H58: 0 | I58: 0 | J58: 0 | K58: 0
E59: Государственные инвестиции | F59: 0 | G59: 165348.7 | H59: 0 | I59: 0 | J59: 0 | K59: 0
A60: 311 | B60: 25 | C60: 920 | D60: 70499 | E60: Модернизация системы налогового администрирования и статистической системы (ВБ) (грант) | F60: 0 | G60: 165348.7 | H60: 0 | I60: 0 | J60: 0 | K60: 0
A61: 311 | B61: 25 | C61: 930 | D61: 70499 | E61: Модернизация системы налогового администрирования и статистической системы (ВБ) (кредит) | F61: 0 | G61: 0 | H61: 0 | I61: 0 | J61: 0 | K61: 0
E63: Министерство просвещения Кыргызской Республики | F63: 88400 | G63: 923780 | H63: 89300 | I63: 1080530 | J63: 71600 | K63: 1543875
E64: Государственные инвестиции | F64: 88400 | G64: 923780 | H64: 89300 | I64: 1080530 | J64: 71600 | K64: 1543875
A65: 311 | B65: 34 | C65: 920 | D65: 70989 | E65: Образование для будущего (ВБ) (грант) | F65: 0 | G65: 0 | H65: 0 | I65: 0 | J65: 0 | K65: 0
A66: 311 | B66: 34 | C66: 930 | D66: 70989 | E66: Образование для будущего (ВБ) (кредит) | F66: 0 | G66: 0 | H66: 0 | I66: 0 | J66: 0 | K66: 0
A67: 311 | B67: 34 | C67: 920 | D67: 70989 | E67: Укрепление основ обучения (ВБ) (грант) | F67: 0 | G67: 0 | H67: 0 | I67: 0 | J67: 0 | K67: 0
A68: 311 | B68: 34 | C68: 910 | D68: 70989 | E68: Программа развития сектора: реформирование системы школьного образования (АБР) (план) | F68: 88400 | G68: 0 | H68: 89300 | I68: 0 | J68: 71600 | K68: 0
A69: 311 | B69: 34 | C69: 920 | D69: 70989 | E69: Программа развития сектора: реформирование сектора школьного образования (АБР) (грант) (план) | F69: 0 | G69: 88400 | H69: 0 | I69: 160740 | J69: 0 | K69: 152150
A70: 311 | B70: 34 | C70: 930 | D70: 70989 | E70: Программа развития сектора: реформирование сектора школьного образования (АБР) (кредит) (план) | F70: 0 | G70: 424320 | H70: 0 | I70: 437570 | J70: 0 | K70: 698100
A71: 311 | B71: 34 | C71: 930 | D71: 70989 | E71: Качество высшего образования и инновации (ВБ) (кредит) (план) | F71: 0 | G71: 411060 | H71: 0 | I71: 482220 | J71: 0 | K71: 693625
A72: 311 | B72: 34 | C72: 910 | D72: 70989 | E72: Smart-Ed по улучшению доступа к возможностям инклюзивного обучения и его качества для всех детей в Кыргызской Республике» | F72: 0 | G72: 0 | H72: 0 | I72: 0 | J72: 0 | K72: 0
A73: 311 | B73: 34 | C73: 920 | D73: 70989 | E73: Smart-Ed по улучшению доступа к возможностям инклюзивного обучения и его качества для всех детей в Кыргызской Республике» (ИФСР) (грант) | F73: 0 | G73: 0 | H73: 0 | I73: 0 | J73: 0 | K73: 0
A74: 311 | B74: 34 | C74: 920 | D74: 70989 | E74: Smart-Ed по улучшению доступа к возможностям инклюзивного обучения и его качества для всех детей в Кыргызской Республике» (ИБР) (грант) | F74: 0 | G74: 0 | H74: 0 | I74: 0 | J74: 0 | K74: 0
A75: 311 | B75: 34 | C75: 930 | D75: 70989 | E75: Smart-Ed по улучшению доступа к возможностям инклюзивного обучения и его качества для всех детей в Кыргызской Республике» (ИБР) (кредит) | F75: 0 | G75: 0 | H75: 0 | I75: 0 | J75: 0 | K75: 0
A76: 311 | B76: 34 | C76: 920 | D76: 70989 | E76: Smart-Ed по улучшению доступа к возможностям инклюзивного обучения и его качества для всех детей в Кыргызской Республике» | F76: 0 | G76: 0 | H76: 0 | I76: 0 | J76: 0 | K76: 0
A77: 311 | B77: 34 | C77: 920 | D77: 70989 | E77: Образование для будущего (ВБ) (грант) ДФ | F77: 0 | G77: 0 | H77: 0 | I77: 0 | J77: 0 | K77: 0
A78: 311 | B78: 34 | C78: 930 | D78: 70989 | E78: Образование для будущего (ВБ) (кредит) ДФ
A79: 311 | B79: 34 | C79: 910 | D79: 70989 | E79: Проект по подготовке Программы трансформации школьного и начального профессионального образования
A80: 311 | B80: 34 | C80: 920 | D80: 70989 | E80: Проект по подготовке Программы трансформации школьного и начального профессионального образования (грант)
E82: Министерство здравоохранения Кыргызской Республики | F82: 85173.4 | G82: 2502849.8 | H82: 80370 | I82: 2218015.6 | J82: 13425 | K82: 906222.5
E83: Государственные инвестиции | F83: 85173.4 | G83: 2502849.8 | H83: 80370 | I83: 2218015.6 | J83: 13425 | K83: 906222.5
A84: 311 | B84: 37 | C84: 920 | D84: 70769 | E84: Проект «Здравоохранение и социальная защита» – 3, 4 (КфВ) (грант) | F84: 0 | G84: 3400.7 | H84: 0 | I84: 0 | J84: 0 | K84: 0
A85: 311 | B85: 37 | C85: 910 | D85: 70769 | E85: Борьба с туберкулезом-V (КфВ) | F85: 0 | G85: 0 | H85: 0 | I85: 0 | J85: 0 | K85: 0
A86: 311 | B86: 37 | C86: 920 | D86: 70769 | E86: Борьба с туберкулезом-V (КфВ) (грант) | F86: 0 | G86: 0 | H86: 0 | I86: 0 | J86: 0 | K86: 0
A87: 311 | B87: 37 | C87: 910 | D87: 70769 | E87: Охрана материнства и детства IV–V (КфВ) | F87: 0 | G87: 0 | H87: 0 | I87: 0 | J87: 0 | K87: 0
A88: 311 | B88: 37 | C88: 920 | D88: 70769 | E88: Охрана материнства и детства IV–V (КфВ) (грант) | F88: 0 | G88: 2278.1 | H88: 0 | I88: 0 | J88: 0 | K88: 0
A89: 311 | B89: 37 | C89: 930 | D89: 70769 | E89: Строительство нового корпуса для Городской детской клинической больницы скорой медицинской помощи города Бишкек (СФР) (кредит) | G89: 695975.9
A90: 311 | B90: 37 | C90: 910 | D90: 70769 | E90: Программа «Охрана материнства и детства» фаза VI–VIII г. Ош (КфВ)
A91: 311 | B91: 37 | C91: 920 | D91: 70769 | E91: Программа «Охрана материнства и детства» фаза VI–VIII г. Ош (КфВ) (грант) | F91: 0 | G91: 217972.3 | H91: 0 | I91: 411137.2 | J91: 0 | K91: 347241.2
A92: 311 | B92: 37 | C92: 910 | D92: 70769 | E92: Программа «Охрана материнства и детства» фаза IХ г. Талас (КфВ)
A93: 311 | B93: 37 | C93: 920 | D93: 70769 | E93: Программа «Охрана материнства и детства» фаза IХ г. Талас (КфВ) (грант) | F93: 0 | G93: 148075.3 | H93: 0 | I93: 202648.5 | J93: 0 | K93: 0
A94: 311 | B94: 37 | C94: 920 | D94: 70769 | E94: Повышение устойчивости к рискам стихийных бедствий в Кыргызстане (ВБ) (грант) | F94: 0 | G94: 0 | H94: 0 | I94: 0 | J94: 0 | K94: 0
A95: 311 | B95: 37 | C95: 930 | D95: 70769 | E95: Повышение устойчивости к рискам стихийных бедствий в Кыргызстане (ВБ) (кредит) | F95: 0 | G95: 0 | H95: 0 | I95: 0 | J95: 0 | K95: 0
A96: 311 | B96: 37 | C96: 910 | D96: 70769 | E96: Проект Функциональное улучшение Республиканской клинической инфекционной больницы (EDCF) (план) | F96: 14453.4 | G96: 0 | H96: 0 | I96: 0 | J96: 0 | K96: 0
A97: 311 | B97: 37 | C97: 930 | D97: 70769 | E97: Проект Функциональное улучшение Республиканской клинической инфекционной больницы (EDCF) (кредит) (план) | F97: 0 | G97: 487676.3 | H97: 0 | I97: 375524.4 | J97: 0 | K97: 495123
A98: 311 | B98: 37 | C98: 910 | D98: 70769 | E98: Укрепление региональной безопасности в области здравоохранения (АБР) (план) | F98: 70720 | G98: 0 | H98: 80370 | I98: 0 | J98: 13425 | K98: 0
A99: 311 | B99: 37 | C99: 920 | D99: 70769 | E99: Укрепление региональной безопасности в области здравоохранения (АБР) (грант) (план) | F99: 0 | G99: 416187.2 | H99: 0 | I99: 420540.5 | J99: 0 | K99: 63858.3
A100: 311 | B100: 37 | C100: 930 | D100: 70769 | E100: Укрепление региональной безопасности в области здравоохранения (АБР) (кредит) (план) | F100: 0 | G100: 283764 | H100: 0 | I100: 56259 | J100: 0 | K100: 0
A101: 311 | B101: 37 | C101: 930 | D101: 70769 | E101: Дополнительное финансирование для Программы повышения качества первичной медико-санитарной помощи (ВБ) (кредит) (план) | F101: 0 | G101: 247520 | H101: 0 | I101: 751906 | J101: 0 | K101: 0
A102: 311 | B102: 37 | C102: 920 | D102: 70769 | E102: Завершающее финансирование инфраструктуры здравоохранения (грант)
A103: 311 | B103: 37 | C103: 930 | D103: 70769 | E103: Строительство нового корпуса Национального госпиталя и обеспечение медицинским оборудованием (ЕДСФ) | F103: 0 | G103: 0 | H103: 0 | I103: 0 | J103: 0 | K103: 0
A104: 311 | B104: 37 | C104: 930 | D104: 70769 | E104: Функциональное улучшение Республиканской клинической инфекционной больницы (ЕДСФ) | F104: 0 | G104: 0 | H104: 0 | I104: 0 | J104: 0 | K104: 0
A105: 311 | B105: 37 | C105: 930 | D105: 70769 | E105: Строительство многопрофильной академической больницы КГМА им. И.К. Ахунбаева (ЕДСФ) | F105: 0 | G105: 0 | H105: 0 | I105: 0 | J105: 0 | K105: 0
A106: 311 | B106: 37 | C106: 930 | D106: 70769 | E106: Дополнительное финансирование для Операции по повышению качества первичной медико-санитарной помощи» | F106: 0 | G106: 0 | H106: 0 | I106: 0 | J106: 0 | K106: 0
A107: 311 | B107: 37 | C107: 910 | D107: 70769 | E107: Модернизация и улучшение инфраструктуры больниц
A108: 311 | B108: 37 | C108: 920 | D108: 70769 | E108: Модернизация и улучшение инфраструктуры больниц (грант)
E110: Министерство труда, социального обеспечения и миграции Кыргызской Республики | F110: 0 | G110: 521560 | H110: 0 | I110: 267900 | J110: 0 | K110: 0
E111: Государственные инвестиции | F111: 0 | G111: 521560 | H111: 0 | I111: 267900 | J111: 0 | K111: 0
A112: 311 | B112: 38 | C112: 930 | D112: 70499 | E112: Укрепление программ социальной помощи и рынка труда (ВБ) (кредит) | F112: 0 | G112: 521560 | H112: 0 | I112: 267900 | J112: 0 | K112: 0
A113: 311 | B113: 38 | C113: 920 | D113: 70499 | E113: Модернизация и устойчивое развитие электроэнергетического сектора (ВБ) (грант) | F113: 0 | G113: 0 | H113: 0 | I113: 0 | J113: 0 | K113: 0
E115: Министерство водных ресурсов, сельского хозяйства, и перерабатывающей промышленности Кыргызской Республики | F115: 17680 | G115: 1922700 | H115: 172349 | I115: 2087110.6 | J115: 179000 | K115: 1894983.5
E116: Государственные инвестиции | F116: 17680 | G116: 1922700 | H116: 172349 | I116: 2087110.6 | J116: 179000 | K116: 1894983.5
A117: 311 | B117: 41 | C117: 920 | D117: 70499 | E117: Комплексное повышение производительности молочного сектора (ВБ) (грант) Дополнительное финансирование | F117: 0 | G117: 0 | H117: 0 | I117: 0 | J117: 0 | K117: 0
...

Sheet СОМ(без формул до десятых) 24
L4: 91.6 | N4: 88.4 | P4: 89.3 | R4: 89.5 | T4: 90 | V4: 90.5
A5: Классификация | E5: донор | F5: Наименование проекта | G5: номер и дата кредитного соглашения | H5: 2024 | L5: 2025 | N5: 2026 | P5: 2027 | R5: 2028 | T5: 2029 | V5: 2030
A6: III | B6: IV | D6: V | H6: Факт внутренний | I6: % к утвержденному | J6: Факт внешний | K6: % к утвержденному | L6: Внутреннее | M6: Внешнее | N6: Внутреннее | O6: Внешнее | P6: Внутреннее | Q6: Внешнее | R6: Внутреннее | S6: Внешнее | T6: Внутреннее | U6: Внешнее | V6: Внутреннее | W6: Внешнее
F7: Министерство финансов КР | L7: =L8 -> #REF! | M7: =M8 -> #REF! | N7: =N8 -> #REF! | O7: =O8 -> #REF! | P7: =P8 -> #REF! | Q7: =Q8 -> #REF! | R7: =R8 -> #REF! | S7: =S8 -> #REF! | ... W7: =W8 -> #REF! | X7: =M7+O7+Q7+S7+U7+W7 -> #REF!
F8: Государственные инвестиции | L8: =SUM(L9:L38) -> #REF! | M8: =SUM(M9:M38) -> #REF! | N8: =SUM(N9:N38) -> #REF! | O8: =SUM(O9:O38) -> #REF! | P8: =SUM(P9:P38) -> #REF! | Q8: =SUM(Q9:Q38) -> #REF! | R8: =SUM(R9:R38) -> #REF! | S8: =SUM(S9:S38) -> #REF! | ... W8: =SUM(W9:W38) -> #REF! | X8: =M8+O8+Q8+S8+U8+W8 -> #REF!
A9: 311 | B9: 25 | C9: 910 | D9: 70499 | F9: Цепочка добавленной стоимости агрофинансирования (КфВ) Фаза 2 | L9: =ROUND(COM!H9,1) -> #REF! | M9: =ROUND(COM!I9,1) -> #REF! | N9: =ROUND(COM!J9,1) -> #REF! | O9: =ROUND(COM!K9,1) -> #REF! | P9: =ROUND(COM!L9,1) -> #REF! | Q9: =ROUND(COM!M9,1) -> #REF! | R9: =ROUND(COM!N9,1) -> #REF! | S9: =ROUND(COM!O9,1) -> #REF! | ... W9: =ROUND(COM!S9,1) -> #REF! | X9: =M9+O9+Q9+S9+U9+W9 -> #REF!
A10: 311 | B10: 25 | C10: 920 | D10: 70499 | E10: КфВ | F10: Цепочка добавленной стоимости агрофинансирования (КфВ) (грант) Фаза 2 | L10: =ROUND(COM!H10,1) -> #REF! | M10: =ROUND(COM!I10,1) -> #REF! | N10: =ROUND(COM!J10,1) -> #REF! | O10: =ROUND(COM!K10,1) -> #REF! | P10: =ROUND(COM!L10,1) -> #REF! | Q10: =ROUND(COM!M10,1) -> #REF! | R10: =ROUND(COM!N10,1) -> #REF! | S10: =ROUND(COM!O10,1) -> #REF! | ... W10: =ROUND(COM!S10,1) -> #REF! | X10: =M10+O10+Q10+S10+U10+W10 -> #REF!
A11: 311 | B11: 25 | C11: 910 | D11: 70499 | F11: Цепочка добавленной стоимости агрофинансирования-2 (ИФЦА) | L11: =ROUND(COM!H11,1) -> #REF! | M11: =ROUND(COM!I11,1) -> #REF! | N11: =ROUND(COM!J11,1) -> #REF! | O11: =ROUND(COM!K11,1) -> #REF! | P11: =ROUND(COM!L11,1) -> #REF! | Q11: =ROUND(COM!M11,1) -> #REF! | R11: =ROUND(COM!N11,1) -> #REF! | S11: =ROUND(COM!O11,1) -> #REF! | ... W11: =ROUND(COM!S11,1) -> #REF! | X11: =M11+O11+Q11+S11+U11+W11 -> #REF!
A12: 311 | B12: 25 | C12: 920 | D12: 70499 | E12: ИФЦА | F12: Цепочка добавленной стоимости агрофинансирования-2 (ИФЦА) (грант) | L12: =ROUND(COM!H12,1) -> #REF! | M12: =ROUND(COM!I12,1) -> #REF! | N12: =ROUND(COM!J12,1) -> #REF! | O12: =ROUND(COM!K12,1) -> #REF! | P12: =ROUND(COM!L12,1) -> #REF! | Q12: =ROUND(COM!M12,1) -> #REF! | R12: =ROUND(COM!N12,1) -> #REF! | S12: =ROUND(COM!O12,1) -> #REF! | ... W12: =ROUND(COM!S12,1) -> #REF! | X12: =M12+O12+Q12+S12+U12+W12 -> #REF!
A13: 321 | B13: 25 | C13: 930 | D13: 70499 | E13: ЕИБ | F13: Цепочка добавленной стоимости агрофинансирования-2 (ЕИБ) (кредит) | G13: FI № 84.373 | L13: =ROUND(COM!H13,1) -> #REF! | M13: =ROUND(COM!I13,1) -> #REF! | N13: =ROUND(COM!J13,1) -> #REF! | O13: =ROUND(COM!K13,1) -> #REF! | P13: =ROUND(COM!L13,1) -> #REF! | Q13: =ROUND(COM!M13,1) -> #REF! | R13: =ROUND(COM!N13,1) -> #REF! | S13: =ROUND(COM!O13,1) -> #REF! | ... W13: =ROUND(COM!S13,1) -> #REF! | X13: =M13+O13+Q13+S13+U13+W13 -> #REF!
A14: 311 | B14: 25 | C14: 920 | D14: 70499 | E14: ВБ | F14: Комплексное повышение производительности молочного сектора (ВБ) (грант) Доп. Финансирование | L14: =ROUND(COM!H14,1) -> #REF! | M14: =ROUND(COM!I14,1) -> #REF! | N14: =ROUND(COM!J14,1) -> #REF! | O14: =ROUND(COM!K14,1) -> #REF! | P14: =ROUND(COM!L14,1) -> #REF! | Q14: =ROUND(COM!M14,1) -> #REF! | R14: =ROUND(COM!N14,1) -> #REF! | S14: =ROUND(COM!O14,1) -> #REF! | ... W14: =ROUND(COM!S14,1) -> #REF! | X14: =M14+O14+Q14+S14+U14+W14 -> #REF!
A15: 321 | B15: 25 | C15: 920 | D15: 70499 | E15: ВБ | F15: Комплексное повышение производительности молочного сектора (ВБ) (грант) Доп. Финансирование | L15: =ROUND(COM!H15,1) -> #REF! | M15: =ROUND(COM!I15,1) -> #REF! | N15: =ROUND(COM!J15,1) -> #REF! | O15: =ROUND(COM!K15,1) -> #REF! | P15: =ROUND(COM!L15,1) -> #REF! | Q15: =ROUND(COM!M15,1) -> #REF! | R15: =ROUND(COM!N15,1) -> #REF! | S15: =ROUND(COM!O15,1) -> #REF! | ... W15: =ROUND(COM!S15,1) -> #REF! | X15: =M15+O15+Q15+S15+U15+W15 -> #REF!
A16: 311 | B16: 25 | C16: 930 | D16: 70499 | E16: ВБ | F16: Комплексное повышение производительности молочного сектора (ВБ) (кредит) Доп. Финансирование | G16: № 6941-KG | L16: =ROUND(COM!H16,1) -> #REF! | M16: =ROUND(COM!I16,1) -> #REF! | N16: =ROUND(COM!J16,1) -> #REF! | O16: =ROUND(COM!K16,1) -> #REF! | P16: =ROUND(COM!L16,1) -> #REF! | Q16: =ROUND(COM!M16,1) -> #REF! | R16: =ROUND(COM!N16,1) -> #REF! | S16: =ROUND(COM!O16,1) -> #REF! | ... W16: =ROUND(COM!S16,1) -> #REF! | X16: =M16+O16+Q16+S16+U16+W16 -> #REF!
A17: 321 | B17: 25 | C17: 930 | D17: 70499 | E17: ВБ | F17: Комплексное повышение производительности молочного сектора (ВБ) (кредит) Доп. Финансирование | L17: =ROUND(COM!H17,1) -> #REF! | M17: =ROUND(COM!I17,1) -> #REF! | N17: =ROUND(COM!J17,1) -> #REF! | O17: =ROUND(COM!K17,1) -> #REF! | P17: =ROUND(COM!L17,1) -> #REF! | Q17: =ROUND(COM!M17,1) -> #REF! | R17: =ROUND(COM!N17,1) -> #REF! | S17: =ROUND(COM!O17,1) -> #REF! | ... W17: =ROUND(COM!S17,1) -> #REF! | X17: =M17+O17+Q17+S17+U17+W17 -> #REF!
A18: 311 | B18: 25 | C18: 920 | D18: 70499 | E18: ВБ | F18: Проект по поддержке частного сектора (ВБ) (грант) | L18: =ROUND(COM!H18,1) -> #REF! | M18: =ROUND(COM!I18,1) -> #REF! | N18: =ROUND(COM!J18,1) -> #REF! | O18: =ROUND(COM!K18,1) -> #REF! | P18: =ROUND(COM!L18,1) -> #REF! | Q18: =ROUND(COM!M18,1) -> #REF! | R18: =ROUND(COM!N18,1) -> #REF! | S18: =ROUND(COM!O18,1) -> #REF! | ... W18: =ROUND(COM!S18,1) -> #REF! | X18: =M18+O18+Q18+S18+U18+W18 -> #REF!
A19: 321 | B19: 25 | C19: 920 | D19: 70499 | E19: ВБ | F19: Проект по поддержке частного сектора (ВБ) (грант) | L19: =ROUND(COM!H19,1) -> #REF! | M19: =ROUND(COM!I19,1) -> #REF! | N19: =ROUND(COM!J19,1) -> #REF! | O19: =ROUND(COM!K19,1) -> #REF! | P19: =ROUND(COM!L19,1) -> #REF! | Q19: =ROUND(COM!M19,1) -> #REF! | R19: =ROUND(COM!N19,1) -> #REF! | S19: =ROUND(COM!O19,1) -> #REF! | ... W19: =ROUND(COM!S19,1) -> #REF! | X19: =M19+O19+Q19+S19+U19+W19 -> #REF!
A20: 321 | B20: 25 | C20: 930 | D20: 70499 | E20: ВБ | F20: Проект по поддержке частного сектора (ВБ) (кредит) | G20: № 6758-KG | L20: =ROUND(COM!H20,1) -> #REF! | M20: =ROUND(COM!I20,1) -> #REF! | N20: =ROUND(COM!J20,1) -> #REF! | O20: =ROUND(COM!K20,1) -> #REF! | P20: =ROUND(COM!L20,1) -> #REF! | Q20: =ROUND(COM!M20,1) -> #REF! | R20: =ROUND(COM!N20,1) -> #REF! | S20: =ROUND(COM!O20,1) -> #REF! | ... W20: =ROUND(COM!S20,1) -> #REF! | X20: =M20+O20+Q20+S20+U20+W20 -> #REF!
A21: 311 | B21: 25 | C21: 930 | D21: 70499 | E21: АБИИ | F21: Проект по поддержке частного сектора (АБИИ) (кредит) | G21: № 0423-А | L21: =ROUND(COM!H21,1) -> #REF! | M21: =ROUND(COM!I21,1) -> #REF! | N21: =ROUND(COM!J21,1) -> #REF! | O21: =ROUND(COM!K21,1) -> #REF! | P21: =ROUND(COM!L21,1) -> #REF! | Q21: =ROUND(COM!M21,1) -> #REF! | R21: =ROUND(COM!N21,1) -> #REF! | S21: =ROUND(COM!O21,1) -> #REF! | ... W21: =ROUND(COM!S21,1) -> #REF! | X21: =M21+O21+Q21+S21+U21+W21 -> #REF!
A22: 321 | B22: 25 | C22: 930 | D22: 70499 | E22: АБИИ | F22: Проект по поддержке частного сектора (АБИИ) (кредит) | L22: =ROUND(COM!H22,1) -> #REF! | M22: =ROUND(COM!I22,1) -> #REF! | N22: =ROUND(COM!J22,1) -> #REF! | O22: =ROUND(COM!K22,1) -> #REF! | P22: =ROUND(COM!L22,1) -> #REF! | Q22: =ROUND(COM!M22,1) -> #REF! | R22: =ROUND(COM!N22,1) -> #REF! | S22: =ROUND(COM!O22,1) -> #REF! | ... W22: =ROUND(COM!S22,1) -> #REF! | X22: =M22+O22+Q22+S22+U22+W22 -> #REF!
A23: 311 | B23: 25 | C23: 920 | D23: 70499 | E23: ВБ | F23: Экстренная поддержка микро, малых и средних предприятий ДФ (ВБ) (грант) | L23: =ROUND(COM!H23,1) -> #REF! | M23: =ROUND(COM!I23,1) -> #REF! | N23: =ROUND(COM!J23,1) -> #REF! | O23: =ROUND(COM!K23,1) -> #REF! | P23: =ROUND(COM!L23,1) -> #REF! | Q23: =ROUND(COM!M23,1) -> #REF! | R23: =ROUND(COM!N23,1) -> #REF! | S23: =ROUND(COM!O23,1) -> #REF! | ... W23: =ROUND(COM!S23,1) -> #REF! | X23: =M23+O23+Q23+S23+U23+W23 -> #REF!
A24: 321 | B24: 25 | C24: 920 | D24: 70499 | E24: ВБ | F24: Экстренная поддержка микро, малых и средних предприятий ДФ (ВБ) (грант) | L24: =ROUND(COM!H24,1) -> #REF! | M24: =ROUND(COM!I24,1) -> #REF! | N24: =ROUND(COM!J24,1) -> #REF! | O24: =ROUND(COM!K24,1) -> #REF! | P24: =ROUND(COM!L24,1) -> #REF! | Q24: =ROUND(COM!M24,1) -> #REF! | R24: =ROUND(COM!N24,1) -> #REF! | S24: =ROUND(COM!O24,1) -> #REF! | ... W24: =ROUND(COM!S24,1) -> #REF! | X24: =M24+O24+Q24+S24+U24+W24 -> #REF!
A25: 321 | B25: 25 | C25: 930 | D25: 70499 | E25: ВБ | F25: Экстренная поддержка микро, малых и средних предприятий ДФ (ВБ) (кредит) | G25: № 7094-KG | L25: =ROUND(COM!H25,1) -> #REF! | M25: =ROUND(COM!I25,1) -> #REF! | N25: =ROUND(COM!J25,1) -> #REF! | O25: =ROUND(COM!K25,1) -> #REF! | P25: =ROUND(COM!L25,1) -> #REF! | Q25: =ROUND(COM!M25,1) -> #REF! | R25: =ROUND(COM!N25,1) -> #REF! | S25: =ROUND(COM!O25,1) -> #REF! | ... W25: =ROUND(COM!S25,1) -> #REF! | X25: =M25+O25+Q25+S25+U25+W25 -> #REF!
A26: 311 | B26: 25 | C26: 930 | D26: 70499 | E26: ВБ | F26: Улучшение качества воздуха в городе Бишкек (ВБ) (кредит) | G26: № 7434-KG | L26: =ROUND(COM!H26,1) -> #REF! | M26: =ROUND(COM!I26,1) -> #REF! | N26: =ROUND(COM!J26,1) -> #REF! | O26: =ROUND(COM!K26,1) -> #REF! | P26: =ROUND(COM!L26,1) -> #REF! | Q26: =ROUND(COM!M26,1) -> #REF! | R26: =ROUND(COM!N26,1) -> #REF! | S26: =ROUND(COM!O26,1) -> #REF! | ... W26: =ROUND(COM!S26,1) -> #REF! | X26: =M26+O26+Q26+S26+U26+W26 -> #REF!
A27: 321 | B27: 25 | C27: 930 | D27: 70499 | E27: ВБ | F27: Улучшение качества воздуха в городе Бишкек (ВБ) (кредит) | L27: =ROUND(COM!H27,1) -> #REF! | M27: =ROUND(COM!I27,1) -> #REF! | N27: =ROUND(COM!J27,1) -> #REF! | O27: =ROUND(COM!K27,1) -> #REF! | P27: =ROUND(COM!L27,1) -> #REF! | Q27: =ROUND(COM!M27,1) -> #REF! | R27: =ROUND(COM!N27,1) -> #REF! | S27: =ROUND(COM!O27,1) -> #REF! | ... W27: =ROUND(COM!S27,1) -> #REF! | X27: =M27+O27+Q27+S27+U27+W27 -> #REF!
A28: 311 | B28: 25 | C28: 930 | D28: 70499 | E28: ВБ | F28: Проект развития устойчивых агропродовольственных кластеров (ВБ) (кредит) | G28: № 7526-KG | L28: =ROUND(COM!H28,1) -> #REF! | M28: =ROUND(COM!I28,1) -> #REF! | N28: =ROUND(COM!J28,1) -> #REF! | O28: =ROUND(COM!K28,1) -> #REF! | P28: =ROUND(COM!L28,1) -> #REF! | Q28: =ROUND(COM!M28,1) -> #REF! | R28: =ROUND(COM!N28,1) -> #REF! | S28: =ROUND(COM!O28,1) -> #REF! | ... W28: =ROUND(COM!S28,1) -> #REF! | X28: =M28+O28+Q28+S28+U28+W28 -> #REF!
A29: 321 | B29: 25 | C29: 930 | D29: 70499 | E29: ВБ | F29: Проект развития устойчивых агропродовольственных кластеров (ВБ) (кредит) | L29: =ROUND(COM!H29,1) -> #REF! | M29: =ROUND(COM!I29,1) -> #REF! | N29: =ROUND(COM!J29,1) -> #REF! | O29: =ROUND(COM!K29,1) -> #REF! | P29: =ROUND(COM!L29,1) -> #REF! | Q29: =ROUND(COM!M29,1) -> #REF! | R29: =ROUND(COM!N29,1) -> #REF! | S29: =ROUND(COM!O29,1) -> #REF! | ... W29: =ROUND(COM!S29,1) -> #REF! | X29: =M29+O29+Q29+S29+U29+W29 -> #REF!
A30: 311 | B30: 25 | C30: 930 | D30: 70499 | E30: ВБ | F30: Развитие устойчивых финансовых рынков для микро-, малых и средних предприятий в Кыргызской Республике (ВБ) (кредит) (план) | G30: 7741-KG | L30: =ROUND(COM!H30,1) -> #REF! | M30: =ROUND(COM!I30,1) -> #REF! | N30: =ROUND(COM!J30,1) -> #REF! | O30: =ROUND(COM!K30,1) -> #REF! | P30: =ROUND(COM!L30,1) -> #REF! | Q30: =ROUND(COM!M30,1) -> #REF! | R30: =ROUND(COM!N30,1) -> #REF! | S30: =ROUND(COM!O30,1) -> #REF! | ... W30: =ROUND(COM!S30,1) -> #REF! | X30: =M30+O30+Q30+S30+U30+W30 -> #REF!
A31: 321 | B31: 25 | C31: 930 | D31: 70499 | E31: ВБ | F31: Развитие устойчивых финансовых рынков для микро-, малых и средних предприятий в Кыргызской Республике (ВБ) (кредит) (план) | L31: =ROUND(COM!H31,1) -> #REF! | M31: =ROUND(COM!I31,1) -> #REF! | N31: =ROUND(COM!J31,1) -> #REF! | O31: =ROUND(COM!K31,1) -> #REF! | P31: =ROUND(COM!L31,1) -> #REF! | Q31: =ROUND(COM!M31,1) -> #REF! | R31: =ROUND(COM!N31,1) -> #REF! | S31: =ROUND(COM!O31,1) -> #REF! | ... W31: =ROUND(COM!S31,1) -> #REF! | X31: =M31+O31+Q31+S31+U31+W31 -> #REF!
A32: 311 | B32: 25 | C32: 920 | D32: 70499 | E32: ВБ | F32: Проект сельских инвестиций - 3 ДФ (ВБ) (грант) | L32: =ROUND(COM!H32,1) -> #REF! | M32: =ROUND(COM!I32,1) -> #REF! | N32: =ROUND(COM!J32,1) -> #REF! | O32: =ROUND(COM!K32,1) -> #REF! | P32: =ROUND(COM!L32,1) -> #REF! | Q32: =ROUND(COM!M32,1) -> #REF! | R32: =ROUND(COM!N32,1) -> #REF! | S32: =ROUND(COM!O32,1) -> #REF! | ... W32: =ROUND(COM!S32,1) -> #REF!
A33: 311 | B33: 25 | C33: 930 | D33: 70499 | E33: ВБ | F33: Проект сельских инвестиций - 3 ДФ (ВБ) (кредит) | L33: =ROUND(COM!H33,1) -> #REF! | M33: =ROUND(COM!I33,1) -> #REF! | N33: =ROUND(COM!J33,1) -> #REF! | O33: =ROUND(COM!K33,1) -> #REF! | P33: =ROUND(COM!L33,1) -> #REF! | Q33: =ROUND(COM!M33,1) -> #REF! | R33: =ROUND(COM!N33,1) -> #REF! | S33: =ROUND(COM!O33,1) -> #REF! | ... W33: =ROUND(COM!S33,1) -> #REF!
X34: =M34+O34+Q34+S34+U34+W34 -> 0
X36: =M36+O36+Q36+S36+U36+W36 -> 0
X37: =M37+O37+Q37+S37+U37+W37 -> 0
X38: =M38+O38+Q38+S38+U38+W38 -> 0
F39: Министерство экономики и коммерции КР | L39: =L40 -> #REF! | M39: =M40 -> #REF! | N39: =N40 -> #REF! | O39: =O40 -> #REF! | P39: =P40 -> #REF! | Q39: =Q40 -> #REF! | R39: =R40 -> #REF! | S39: =S40 -> #REF! | ... W39: =W40 -> #REF! | X39: =M39+O39+Q39+S39+U39+W39 -> #REF!
F40: Государственные инвестиции | L40: =SUM(L41:L68) -> #REF! | M40: =SUM(M41:M68) -> #REF! | N40: =SUM(N41:N68) -> #REF! | O40: =SUM(O41:O68) -> #REF! | P40: =SUM(P41:P68) -> #REF! | Q40: =SUM(Q41:Q68) -> #REF! | R40: =SUM(R41:R68) -> #REF! | S40: =SUM(S41:S68) -> #REF! | ... W40: =SUM(W41:W68) -> #REF! | X40: =M40+O40+Q40+S40+U40+W40 -> #REF!
A41: 311 | B41: 28 | C41: 920 | D41: 70499 | E41: ВБ | F41: Проект регионального экономического развития Ошской области (ВБ) (грант) | G41: Грант D5700-KG/Кредит 6558-KG | L41: =ROUND(COM!H41,1) -> #REF! | M41: =ROUND(COM!I41,1) -> #REF! | N41: =ROUND(COM!J41,1) -> #REF! | O41: =ROUND(COM!K41,1) -> #REF! | P41: =ROUND(COM!L41,1) -> #REF! | Q41: =ROUND(COM!M41,1) -> #REF! | R41: =ROUND(COM!N41,1) -> #REF! | S41: =ROUND(COM!O41,1) -> #REF! | ... W41: =ROUND(COM!S41,1) -> #REF! | X41: =M41+O41+Q41+S41+U41+W41 -> #REF!
A42: 311 | B42: 28 | C42: 930 | D42: 70499 | E42: ВБ | F42: Проект регионального экономического развития Ошской области (ВБ) (кредит) | L42: =ROUND(COM!H42,1) -> #REF! | M42: =ROUND(COM!I42,1) -> #REF! | N42: =ROUND(COM!J42,1) -> #REF! | O42: =ROUND(COM!K42,1) -> #REF! | P42: =ROUND(COM!L42,1) -> #REF! | Q42: =ROUND(COM!M42,1) -> #REF! | R42: =ROUND(COM!N42,1) -> #REF! | S42: =ROUND(COM!O42,1) -> #REF! | ... W42: =ROUND(COM!S42,1) -> #REF! | X42: =M42+O42+Q42+S42+U42+W42 -> #REF!
A43: 311 | B43: 28 | C43: 930 | D43: 70499 | E43: ВБ | F43: Проект регионального экономического развития Ошской области - дополнительное финансирование (ВБ) (кредит) | L43: =ROUND(COM!H43,1) -> #REF! | M43: =ROUND(COM!I43,1) -> #REF! | N43: =ROUND(COM!J43,1) -> #REF! | O43: =ROUND(COM!K43,1) -> #REF! | P43: =ROUND(COM!L43,1) -> #REF! | Q43: =ROUND(COM!M43,1) -> #REF! | R43: =ROUND(COM!N43,1) -> #REF! | S43: =ROUND(COM!O43,1) -> #REF! | ... W43: =ROUND(COM!S43,1) -> #REF! | X43: =M43+O43+Q43+S43+U43+W43 -> #REF!
A44: 311 | B44: 28 | C44: 920 | D44: 70499 | E44: ВБ | F44: Проект регионального экономического развития Баткенской области (ВБ) (грант) | G44: Грант D976-KG/Кредит 70490-KG | L44: =ROUND(COM!H44,1) -> #REF! | M44: =ROUND(COM!I44,1) -> #REF! | N44: =ROUND(COM!J44,1) -> #REF! | O44: =ROUND(COM!K44,1) -> #REF! | P44: =ROUND(COM!L44,1) -> #REF! | Q44: =ROUND(COM!M44,1) -> #REF! | R44: =ROUND(COM!N44,1) -> #REF! | S44: =ROUND(COM!O44,1) -> #REF! | ... W44: =ROUND(COM!S44,1) -> #REF! | X44: =M44+O44+Q44+S44+U44+W44 -> #REF!
A45: 311 | B45: 28 | C45: 930 | D45: 70499 | E45: ВБ | F45: Проект регионального экономического развития Баткенской области (ВБ) (кредит) | L45: =ROUND(COM!H45,1) -> #REF! | M45: =ROUND(COM!I45,1) -> #REF! | N45: =ROUND(COM!J45,1) -> #REF! | O45: =ROUND(COM!K45,1) -> #REF! | P45: =ROUND(COM!L45,1) -> #REF! | Q45: =ROUND(COM!M45,1) -> #REF! | R45: =ROUND(COM!N45,1) -> #REF! | S45: =ROUND(COM!O45,1) -> #REF! | ... W45: =ROUND(COM!S45,1) -> #REF! | X45: =M45+O45+Q45+S45+U45+W45 -> #REF!
A46: 311 | B46: 28 | C46: 920 | D46: 70499 | E46: ВБ | F46: Национальный проект по инициативе сообществ (ВБ) (грант) | G46: Грант D976-KG, Кредит 7049-KG | L46: =ROUND(COM!H46,1) -> #REF! | M46: =ROUND(COM!I46,1) -> #REF! | N46: =ROUND(COM!J46,1) -> #REF! | O46: =ROUND(COM!K46,1) -> #REF! | P46: =ROUND(COM!L46,1) -> #REF! | Q46: =ROUND(COM!M46,1) -> #REF! | R46: =ROUND(COM!N46,1) -> #REF! | S46: =ROUND(COM!O46,1) -> #REF! | ... W46: =ROUND(COM!S46,1) -> #REF! | X46: =M46+O46+Q46+S46+U46+W46 -> #REF!
A47: 311 | B47: 28 | C47: 930 | D47: 70499 | E47: ВБ | F47: Национальный проект по инициативе сообществ (ВБ) (кредит) | L47: =ROUND(COM!H47,1) -> #REF! | M47: =ROUND(COM!I47,1) -> #REF! | N47: =ROUND(COM!J47,1) -> #REF! | O47: =ROUND(COM!K47,1) -> #REF! | P47: =ROUND(COM!L47,1) -> #REF! | Q47: =ROUND(COM!M47,1) -> #REF! | R47: =ROUND(COM!N47,1) -> #REF! | S47: =ROUND(COM!O47,1) -> #REF! | ... W47: =ROUND(COM!S47,1) -> #REF! | X47: =M47+O47+Q47+S47+U47+W47 -> #REF!
A48: 311 | B48: 28 | C48: 910 | D48: 70499 | F48: Деятельность «Развитие центра бизнес-услуг», SEFF 2 (АБР) (план) | L48: =ROUND(COM!H48,1) -> #REF! | M48: =ROUND(COM!I48,1) -> #REF! | N48: =ROUND(COM!J48,1) -> #REF! | O48: =ROUND(COM!K48,1) -> #REF! | P48: =ROUND(COM!L48,1) -> #REF! | Q48: =ROUND(COM!M48,1) -> #REF! | R48: =ROUND(COM!N48,1) -> #REF! | S48: =ROUND(COM!O48,1) -> #REF! | ... W48: =ROUND(COM!S48,1) -> #REF!
A49: 311 | B49: 28 | C49: 920 | D49: 70499 | E49: АБР | F49: Деятельность «Развитие центра бизнес-услуг», SEFF 2 (АБР) (грант) (план) | L49: =ROUND(COM!H49,1) -> #REF! | M49: =ROUND(COM!I49,1) -> #REF! | N49: =ROUND(COM!J49,1) -> #REF! | O49: =ROUND(COM!K49,1) -> #REF! | P49: =ROUND(COM!L49,1) -> #REF! | Q49: =ROUND(COM!M49,1) -> #REF! | R49: =ROUND(COM!N49,1) -> #REF! | S49: =ROUND(COM!O49,1) -> #REF! | ... W49: =ROUND(COM!S49,1) -> #REF!
A50: 311 | B50: 28 | C50: 910 | D50: 70499 | F50: Энергоэффективность в общественных зданиях (АБР) (план) | L50: =ROUND(COM!H50,1) -> #REF! | M50: =ROUND(COM!I50,1) -> #REF! | N50: =ROUND(COM!J50,1) -> #REF! | O50: =ROUND(COM!K50,1) -> #REF! | P50: =ROUND(COM!L50,1) -> #REF! | Q50: =ROUND(COM!M50,1) -> #REF! | R50: =ROUND(COM!N50,1) -> #REF! | S50: =ROUND(COM!O50,1) -> #REF! | ... W50: =ROUND(COM!S50,1) -> #REF!
A51: 311 | B51: 28 | C51: 920 | D51: 70499 | E51: АБР | F51: Энергоэффективность в общественных зданиях (АБР) (грант) (план) | L51: =ROUND(COM!H51,1) -> #REF! | M51: =ROUND(COM!I51,1) -> #REF! | N51: =ROUND(COM!J51,1) -> #REF! | O51: =ROUND(COM!K51,1) -> #REF! | P51: =ROUND(COM!L51,1) -> #REF! | Q51: =ROUND(COM!M51,1) -> #REF! | R51: =ROUND(COM!N51,1) -> #REF! | S51: =ROUND(COM!O51,1) -> #REF! | ... W51: =ROUND(COM!S51,1) -> #REF!
A52: 311 | B52: 28 | C52: 930 | D52: 70499 | E52: АБР | F52: Энергоэффективность в общественных зданиях (АБР) (кредит) (план) | L52: =ROUND(COM!H52,1) -> #REF! | M52: =ROUND(COM!I52,1) -> #REF! | N52: =ROUND(COM!J52,1) -> #REF! | O52: =ROUND(COM!K52,1) -> #REF! | P52: =ROUND(COM!L52,1) -> #REF! | Q52: =ROUND(COM!M52,1) -> #REF! | R52: =ROUND(COM!N52,1) -> #REF! | S52: =ROUND(COM!O52,1) -> #REF! | ... W52: =ROUND(COM!S52,1) -> #REF!
A53: 311 | B53: 28 | C53: 920 | D53: 70499 | E53: КфВ | F53: Программа жилищного финансирования (КфВ) (грант) | L53: =ROUND(COM!H53,1) -> #REF! | M53: =ROUND(COM!I53,1) -> #REF! | N53: =ROUND(COM!J53,1) -> #REF! | O53: =ROUND(COM!K53,1) -> #REF! | P53: =ROUND(COM!L53,1) -> #REF! | Q53: =ROUND(COM!M53,1) -> #REF! | R53: =ROUND(COM!N53,1) -> #REF! | S53: =ROUND(COM!O53,1) -> #REF! | ... W53: =ROUND(COM!S53,1) -> #REF! | X53: =M53+O53+Q53+S53+U53+W53 -> #REF!
A54: 311 | B54: 28 | C54: 920 | D54: 70499 | E54: КфВ | F54: Программа жилищного финансирования (КфВ) (грант) Фаза 2 (план) | L54: =ROUND(COM!H54,1) -> #REF! | M54: =ROUND(COM!I54,1) -> #REF! | N54: =ROUND(COM!J54,1) -> #REF! | O54: =ROUND(COM!K54,1) -> #REF! | P54: =ROUND(COM!L54,1) -> #REF! | Q54: =ROUND(COM!M54,1) -> #REF! | R54: =ROUND(COM!N54,1) -> #REF! | S54: =ROUND(COM!O54,1) -> #REF! | ... W54: =ROUND(COM!S54,1) -> #REF! | X54: =M54+O54+Q54+S54+U54+W54 -> #REF!
A55: 311 | B55: 28 | C55: 910 | D55: 70499 | F55: Строительство многоэтажных социальных жилых домов (СФР) | L55: =ROUND(COM!H55,1) -> #REF! | M55: =ROUND(COM!I55,1) -> #REF! | N55: =ROUND(COM!J55,1) -> #REF! | O55: =ROUND(COM!K55,1) -> #REF! | P55: =ROUND(COM!L55,1) -> #REF! | Q55: =ROUND(COM!M55,1) -> #REF! | R55: =ROUND(COM!N55,1) -> #REF! | S55: =ROUND(COM!O55,1) -> #REF! | ... W55: =ROUND(COM!S55,1) -> #REF!
A56: 321 | B56: 28 | C56: 930 | D56: 70499 | E56: СФР | F56: Строительство многоэтажных социальных жилых домов (СФР) (кредит) | G56: 09/789 | L56: =ROUND(COM!H56,1) -> #REF! | M56: =ROUND(COM!I56,1) -> #REF! | N56: =ROUND(COM!J56,1) -> #REF! | O56: =ROUND(COM!K56,1) -> #REF! | P56: =ROUND(COM!L56,1) -> #REF! | Q56: =ROUND(COM!M56,1) -> #REF! | R56: =ROUND(COM!N56,1) -> #REF! | S56: =ROUND(COM!O56,1) -> #REF! | ... W56: =ROUND(COM!S56,1) -> #REF! | X56: =M56+O56+Q56+S56+U56+W56 -> #REF!
A57: 311 | B57: 28 | C57: 910 | D57: 70499 | F57: Финансирование доступного жилья по стандартам шариата (ИБР) | L57: =ROUND(COM!H57,1) -> #REF! | M57: =ROUND(COM!I57,1) -> #REF! | N57: =ROUND(COM!J57,1) -> #REF! | O57: =ROUND(COM!K57,1) -> #REF! | P57: =ROUND(COM!L57,1) -> #REF! | Q57: =ROUND(COM!M57,1) -> #REF! | R57: =ROUND(COM!N57,1) -> #REF! | S57: =ROUND(COM!O57,1) -> #REF! | ... W57: =ROUND(COM!S57,1) -> #REF!
A58: 311 | B58: 28 | C58: 930 | D58: 70499 | E58: ИБР | F58: Финансирование доступного жилья по стандартам шариата (ИБР) (кредит) | G58: KGZ-1028 | L58: =ROUND(COM!H58,1) -> #REF! | M58: =ROUND(COM!I58,1) -> #REF! | N58: =ROUND(COM!J58,1) -> #REF! | O58: =ROUND(COM!K58,1) -> #REF! | P58: =ROUND(COM!L58,1) -> #REF! | Q58: =ROUND(COM!M58,1) -> #REF! | R58: =ROUND(COM!N58,1) -> #REF! | S58: =ROUND(COM!O58,1) -> #REF! | ... W58: =ROUND(COM!S58,1) -> #REF! | X58: =M58+O58+Q58+S58+U58+W58 -> #REF!
A59: 321 | B59: 28 | C59: 930 | D59: 70499 | E59: ИБР | F59: Финансирование доступного жилья по стандартам шариата (ИБР) (кредит) | L59: =ROUND(COM!H59,1) -> #REF! | M59: =ROUND(COM!I59,1) -> #REF! | N59: =ROUND(COM!J59,1) -> #REF! | O59: =ROUND(COM!K59,1) -> #REF! | P59: =ROUND(COM!L59,1) -> #REF! | Q59: =ROUND(COM!M59,1) -> #REF! | R59: =ROUND(COM!N59,1) -> #REF! | S59: =ROUND(COM!O59,1) -> #REF! | ... W59: =ROUND(COM!S59,1) -> #REF! | X59: =M59+O59+Q59+S59+U59+W59 -> #REF!
A60: 311 | B60: 28 | C60: 910 | D60: 70499 | F60: Расширение доступа к доступному и энергоэффективному жилью (АБР) (план) | L60: =ROUND(COM!H60,1) -> #REF! | M60: =ROUND(COM!I60,1) -> #REF! | N60: =ROUND(COM!J60,1) -> #REF! | O60: =ROUND(COM!K60,1) -> #REF! | P60: =ROUND(COM!L60,1) -> #REF! | Q60: =ROUND(COM!M60,1) -> #REF! | R60: =ROUND(COM!N60,1) -> #REF! | S60: =ROUND(COM!O60,1) -> #REF! | ... W60: =ROUND(COM!S60,1) -> #REF!
A61: 321 | B61: 28 | C61: 920 | D61: 70499 | E61: АБР | F61: Расширение доступа к доступному и энергоэффективному жилью (АБР) (грант) (план) | L61: =ROUND(COM!H61,1) -> #REF! | M61: =ROUND(COM!I61,1) -> #REF! | N61: =ROUND(COM!J61,1) -> #REF! | O61: =ROUND(COM!K61,1) -> #REF! | P61: =ROUND(COM!L61,1) -> #REF! | Q61: =ROUND(COM!M61,1) -> #REF! | R61: =ROUND(COM!N61,1) -> #REF! | S61: =ROUND(COM!O61,1) -> #REF! | ... W61: =ROUND(COM!S61,1) -> #REF! | X61: =M61+O61+Q61+S61+U61+W61 -> #REF!
A62: 321 | B62: 28 | C62: 930 | D62: 70499 | E62: АБР | F62: Расширение доступа к доступному и энергоэффективному жилью (АБР) (кредит) (план) | L62: =ROUND(COM!H62,1) -> #REF! | M62: =ROUND(COM!I62,1) -> #REF! | N62: =ROUND(COM!J62,1) -> #REF! | O62: =ROUND(COM!K62,1) -> #REF! | P62: =ROUND(COM!L62,1) -> #REF! | Q62: =ROUND(COM!M62,1) -> #REF! | R62: =ROUND(COM!N62,1) -> #REF! | S62: =ROUND(COM!O62,1) -> #REF! | ... W62: =ROUND(COM!S62,1) -> #REF! | X62: =M62+O62+Q62+S62+U62+W62 -> #REF!
A63: 321 | B63: 28 | C63: 930 | D63: 70499 | E63: EDCF | F63: Строительство социального жилья (EDCF) (кредит) (план) | L63: =ROUND(COM!H63,1) -> #REF! | M63: =ROUND(COM!I63,1) -> #REF! | N63: =ROUND(COM!J63,1) -> #REF! | O63: =ROUND(COM!K63,1) -> #REF! | P63: =ROUND(COM!L63,1) -> #REF! | Q63: =ROUND(COM!M63,1) -> #REF! | R63: =ROUND(COM!N63,1) -> #REF! | S63: =ROUND(COM!O63,1) -> #REF! | ... W63: =ROUND(COM!S63,1) -> #REF!
X67: =M67+O67+Q67+S67+U67+W67 -> 0
X68: =M68+O68+Q68+S68+U68+W68 -> 0
F69: Государственная налоговая служба при Министерстве финансов КР | L69: =L70 -> #REF! | M69: =M70 -> #REF! | N69: =N70 -> #REF! | O69: =O70 -> #REF! | P69: =P70 -> #REF! | Q69: =Q70 -> #REF! | R69: =R70 -> #REF! | S69: =S70 -> #REF! | ... W69: =W70 -> #REF! | X69: =M69+O69+Q69+S69+U69+W69 -> #REF!
F70: Государственные инвестиции | L70: =SUM(L71:L72) -> #REF! | M70: =SUM(M71:M72) -> #REF! | N70: =SUM(N71:N72) -> #REF! | O70: =SUM(O71:O72) -> #REF! | P70: =SUM(P71:P72) -> #REF! | Q70: =SUM(Q71:Q72) -> #REF! | R70: =SUM(R71:R72) -> #REF! | S70: =SUM(S71:S72) -> #REF! | ... W70: =SUM(W71:W72) -> #REF! | X70: =M70+O70+Q70+S70+U70+W70 -> #REF!
A71: 311 | B71: 25 | C71: 920 | D71: 70499 | E71: ВБ | F71: Модернизация системы налогового администрирования и статистической системы (ВБ) (грант) | L71: =ROUND(COM!H71,1) -> #REF! | M71: =ROUND(COM!I71,1) -> #REF! | N71: =ROUND(COM!J71,1) -> #REF! | O71: =ROUND(COM!K71,1) -> #REF! | P71: =ROUND(COM!L71,1) -> #REF! | Q71: =ROUND(COM!M71,1) -> #REF! | R71: =ROUND(COM!N71,1) -> #REF! | S71: =ROUND(COM!O71,1) -> #REF! | ... W71: =ROUND(COM!S71,1) -> #REF! | X71: =M71+O71+Q71+S71+U71+W71 -> #REF!
A72: 311 | B72: 25 | C72: 930 | D72: 70499 | E72: ВБ | F72: Модернизация системы налогового администрирования и статистической системы (ВБ) (кредит) | G72: 6546-KG | L72: =ROUND(COM!H72,1) -> #REF! | M72: =ROUND(COM!I72,1) -> #REF! | N72: =ROUND(COM!J72,1) -> #REF! | O72: =ROUND(COM!K72,1) -> #REF! | P72: =ROUND(COM!L72,1) -> #REF! | Q72: =ROUND(COM!M72,1) -> #REF! | R72: =ROUND(COM!N72,1) -> #REF! | S72: =ROUND(COM!O72,1) -> #REF! | ... W72: =ROUND(COM!S72,1) -> #REF! | X72: =M72+O72+Q72+S72+U72+W72 -> #REF!
X73: =M73+O73+Q73+S73+U73+W73 -> 0
X74: =M74+O74+Q74+S74+U74+W74 -> 0
X75: =M75+O75+Q75+S75+U75+W75 -> 0
X76: =M76+O76+Q76+S76+U76+W76 -> 0
X77: =M77+O77+Q77+S77+U77+W77 -> 0
F78: Министерство образования и науки КР | L78: =L79 -> #REF! | M78: =M79 -> #REF! | N78: =N79 -> #REF! | O78: =O79 -> #REF! | P78: =P79 -> #REF! | Q78: =Q79 -> #REF! | R78: =R79 -> #REF! | S78: =S79 -> #REF! | ... W78: =W79 -> #REF! | X78: =M78+O78+Q78+S78+U78+W78 -> #REF!
F79: Государственные инвестиции | L79: =SUM(L80:L94) -> #REF! | M79: =SUM(M80:M94) -> #REF! | N79: =SUM(N80:N94) -> #REF! | O79: =SUM(O80:O94) -> #REF! | P79: =SUM(P80:P94) -> #REF! | Q79: =SUM(Q80:Q94) -> #REF! | R79: =SUM(R80:R94) -> #REF! | S79: =SUM(S80:S94) -> #REF! | ... W79: =SUM(W80:W94) -> #REF! | X79: =M79+O79+Q79+S79+U79+W79 -> #REF!
A80: 311 | B80: 34 | C80: 920 | D80: 70989 | E80: ВБ | F80: Образование для будущего (ВБ) (грант) | L80: =ROUND(COM!H80,1) -> #REF! | M80: =ROUND(COM!I80,1) -> #REF! | N80: =ROUND(COM!J80,1) -> #REF! | O80: =ROUND(COM!K80,1) -> #REF! | P80: =ROUND(COM!L80,1) -> #REF! | Q80: =ROUND(COM!M80,1) -> #REF! | R80: =ROUND(COM!N80,1) -> #REF! | S80: =ROUND(COM!O80,1) -> #REF! | ... W80: =ROUND(COM!S80,1) -> #REF! | X80: =M80+O80+Q80+S80+U80+W80 -> #REF!
A81: 311 | B81: 34 | C81: 930 | D81: 70989 | E81: ВБ | F81: Образование для будущего (ВБ) (кредит) | G81: 6563-KG | L81: =ROUND(COM!H81,1) -> #REF! | M81: =ROUND(COM!I81,1) -> #REF! | N81: =ROUND(COM!J81,1) -> #REF! | O81: =ROUND(COM!K81,1) -> #REF! | P81: =ROUND(COM!L81,1) -> #REF! | Q81: =ROUND(COM!M81,1) -> #REF! | R81: =ROUND(COM!N81,1) -> #REF! | S81: =ROUND(COM!O81,1) -> #REF! | ... W81: =ROUND(COM!S81,1) -> #REF! | X81: =M81+O81+Q81+S81+U81+W81 -> #REF!
A82: 311 | B82: 34 | C82: 920 | D82: 70989 | E82: ВБ | F82: Укрепление основ обучения (ВБ) (грант) | L82: =ROUND(COM!H82,1) -> #REF! | M82: =ROUND(COM!I82,1) -> #REF! | N82: =ROUND(COM!J82,1) -> #REF! | O82: =ROUND(COM!K82,1) -> #REF! | P82: =ROUND(COM!L82,1) -> #REF! | Q82: =ROUND(COM!M82,1) -> #REF! | R82: =ROUND(COM!N82,1) -> #REF! | S82: =ROUND(COM!O82,1) -> #REF! | ... W82: =ROUND(COM!S82,1) -> #REF! | X82: =M82+O82+Q82+S82+U82+W82 -> #REF!
A83: 311 | B83: 34 | C83: 910 | D83: 70989 | F83: Программа развития сектора: реформирование системы школьного образования (АБР) (план) | L83: =ROUND(COM!H83,1) -> #REF! | M83: =ROUND(COM!I83,1) -> #REF! | N83: =ROUND(COM!J83,1) -> #REF! | O83: =ROUND(COM!K83,1) -> #REF! | P83: =ROUND(COM!L83,1) -> #REF! | Q83: =ROUND(COM!M83,1) -> #REF! | R83: =ROUND(COM!N83,1) -> #REF! | S83: =ROUND(COM!O83,1) -> #REF! | ... W83: =ROUND(COM!S83,1) -> #REF! | X83: =M83+O83+Q83+S83+U83+W83 -> #REF!
A84: 311 | B84: 34 | C84: 920 | D84: 70989 | E84: АБР | F84: Программа развития сектора: реформирование сектора школьного образования (АБР) (грант) (план) | G84: №0851 | L84: =ROUND(COM!H84,1) -> #REF! | M84: =ROUND(COM!I84,1) -> #REF! | N84: =ROUND(COM!J84,1) -> #REF! | O84: =ROUND(COM!K84,1) -> #REF! | P84: =ROUND(COM!L84,1) -> #REF! | Q84: =ROUND(COM!M84,1) -> #REF! | R84: =ROUND(COM!N84,1) -> #REF! | S84: =ROUND(COM!O84,1) -> #REF! | ... W84: =ROUND(COM!S84,1) -> #REF! | X84: =M84+O84+Q84+S84+U84+W84 -> #REF!
A85: 311 | B85: 34 | C85: 930 | D85: 70989 | E85: АБР | F85: Программа развития сектора: реформирование сектора школьного образования (АБР) (кредит) (план) | G85: №4217 | L85: =ROUND(COM!H85,1) -> #REF! | M85: =ROUND(COM!I85,1) -> #REF! | N85: =ROUND(COM!J85,1) -> #REF! | O85: =ROUND(COM!K85,1) -> #REF! | P85: =ROUND(COM!L85,1) -> #REF! | Q85: =ROUND(COM!M85,1) -> #REF! | R85: =ROUND(COM!N85,1) -> #REF! | S85: =ROUND(COM!O85,1) -> #REF! | ... W85: =ROUND(COM!S85,1) -> #REF! | X85: =M85+O85+Q85+S85+U85+W85 -> #REF!
A86: 311 | B86: 34 | C86: 930 | D86: 70989 | E86: ВБ | F86: Качество высшего образования и инновации (ВБ) (кредит) (план) | G86: 7480-KG | L86: =ROUND(COM!H86,1) -> #REF! | M86: =ROUND(COM!I86,1) -> #REF! | N86: =ROUND(COM!J86,1) -> #REF! | O86: =ROUND(COM!K86,1) -> #REF! | P86: =ROUND(COM!L86,1) -> #REF! | Q86: =ROUND(COM!M86,1) -> #REF! | R86: =ROUND(COM!N86,1) -> #REF! | S86: =ROUND(COM!O86,1) -> #REF! | ... W86: =ROUND(COM!S86,1) -> #REF! | X86: =M86+O86+Q86+S86+U86+W86 -> #REF!
A87: 311 | B87: 34 | C87: 920 | D87: 70989 | E87: ЕФСР | F87: Smart-Ed по улучшению доступа к возможностям инклюзивного обучения и его качества для всех детей в Кыргызской Республике» (ЕФСР) (грант) | L87: =ROUND(COM!H87,1) -> #REF! | M87: =ROUND(COM!I87,1) -> #REF! | N87: =ROUND(COM!J87,1) -> #REF! | O87: =ROUND(COM!K87,1) -> #REF! | P87: =ROUND(COM!L87,1) -> #REF! | Q87: =ROUND(COM!M87,1) -> #REF! | R87: =ROUND(COM!N87,1) -> #REF! | S87: =ROUND(COM!O87,1) -> #REF! | ... W87: =ROUND(COM!S87,1) -> #REF! | X87: =M87+O87+Q87+S87+U87+W87 -> #REF!
A88: 311 | B88: 34 | C88: 920 | D88: 70989 | E88: ИБР | F88: Smart-Ed по улучшению доступа к возможностям инклюзивного обучения и его качества для всех детей в Кыргызской Республике» (ИБР) (грант) | L88: =ROUND(COM!H88,1) -> #REF! | M88: =ROUND(COM!I88,1) -> #REF! | N88: =ROUND(COM!J88,1) -> #REF! | O88: =ROUND(COM!K88,1) -> #REF! | P88: =ROUND(COM!L88,1) -> #REF! | Q88: =ROUND(COM!M88,1) -> #REF! | R88: =ROUND(COM!N88,1) -> #REF! | S88: =ROUND(COM!O88,1) -> #REF! | ... W88: =ROUND(COM!S88,1) -> #REF!
A89: 311 | B89: 34 | C89: 930 | D89: 70989 | E89: ИБР | F89: Smart-Ed по улучшению доступа к возможностям инклюзивного обучения и его качества для всех детей в Кыргызской Республике» (ИБР) (кредит) | L89: =ROUND(COM!H89,1) -> #REF! | M89: =ROUND(COM!I89,1) -> #REF! | N89: =ROUND(COM!J89,1) -> #REF! | O89: =ROUND(COM!K89,1) -> #REF! | P89: =ROUND(COM!L89,1) -> #REF! | Q89: =ROUND(COM!M89,1) -> #REF! | R89: =ROUND(COM!N89,1) -> #REF! | S89: =ROUND(COM!O89,1) -> #REF! | ... W89: =ROUND(COM!S89,1) -> #REF! | X89: =M89+O89+Q89+S89+U89+W89 -> #REF!
A90: 311 | B90: 34 | C90: 920 | D90: 70989 | E90: ГПЦО | F90: Smart-Ed по улучшению доступа к возможностям инклюзивного обучения и его качества для всех детей в Кыргызской Республике» | L90: =ROUND(COM!H90,1) -> #REF! | M90: =ROUND(COM!I90,1) -> #REF! | N90: =ROUND(COM!J90,1) -> #REF! | O90: =ROUND(COM!K90,1) -> #REF! | P90: =ROUND(COM!L90,1) -> #REF! | Q90: =ROUND(COM!M90,1) -> #REF! | R90: =ROUND(COM!N90,1) -> #REF! | S90: =ROUND(COM!O90,1) -> #REF! | ... W90: =ROUND(COM!S90,1) -> #REF!
A91: 311 | B91: 34 | C91: 920 | D91: 70989 | E91: ВБ | F91: Образование для будущего (ВБ) (грант) ДФ | L91: =ROUND(COM!H91,1) -> #REF! | M91: =ROUND(COM!I91,1) -> #REF! | N91: =ROUND(COM!J91,1) -> #REF! | O91: =ROUND(COM!K91,1) -> #REF! | P91: =ROUND(COM!L91,1) -> #REF! | Q91: =ROUND(COM!M91,1) -> #REF! | R91: =ROUND(COM!N91,1) -> #REF! | S91: =ROUND(COM!O91,1) -> #REF! | ... W91: =ROUND(COM!S91,1) -> #REF! | X91: =M91+O91+Q91+S91+U91+W91 -> #REF!
X93: =M93+O93+Q93+S93+U93+W93 -> 0
X94: =M94+O94+Q94+S94+U94+W94 -> 0
F95: Министерство здравоохранения КР | L95: =L96 -> #REF! | M95: =M96 -> #REF! | N95: =N96 -> #REF! | O95: =O96 -> #REF! | P95: =P96 -> #REF! | Q95: =Q96 -> #REF! | R95: =R96 -> #REF! | S95: =S96 -> #REF! | ... W95: =W96 -> #REF! | X95: =M95+O95+Q95+S95+U95+W95 -> #REF!
F96: Государственные инвестиции | L96: =SUM(L97:L126) -> #REF! | M96: =SUM(M97:M126) -> #REF! | N96: =SUM(N97:N126) -> #REF! | O96: =SUM(O97:O126) -> #REF! | P96: =SUM(P97:P126) -> #REF! | Q96: =SUM(Q97:Q126) -> #REF! | R96: =SUM(R97:R126) -> #REF! | S96: =SUM(S97:S126) -> #REF! | ... W96: =SUM(W97:W126) -> #REF! | X96: =M96+O96+Q96+S96+U96+W96 -> #REF!
A97: 311 | B97: 37 | C97: 920 | D97: 70769 | E97: КфВ | F97: Создание национальной системы экстренной медицины (КфВ) - 1 (грант) | L97: =ROUND(COM!H97,1) -> #REF! | M97: =ROUND(COM!I97,1) -> #REF! | N97: =ROUND(COM!J97,1) -> #REF! | O97: =ROUND(COM!K97,1) -> #REF! | P97: =ROUND(COM!L97,1) -> #REF! | Q97: =ROUND(COM!M97,1) -> #REF! | R97: =ROUND(COM!N97,1) -> #REF! | S97: =ROUND(COM!O97,1) -> #REF! | ... W97: =ROUND(COM!S97,1) -> #REF! | X97: =M97+O97+Q97+S97+U97+W97 -> #REF!
A98: 311 | B98: 37 | C98: 910 | D98: 70769 | F98: Создание национальной системы экстренной медицины (КфВ) | L98: =ROUND(COM!H98,1) -> #REF! | M98: =ROUND(COM!I98,1) -> #REF! | N98: =ROUND(COM!J98,1) -> #REF! | O98: =ROUND(COM!K98,1) -> #REF! | P98: =ROUND(COM!L98,1) -> #REF! | Q98: =ROUND(COM!M98,1) -> #REF! | R98: =ROUND(COM!N98,1) -> #REF! | S98: =ROUND(COM!O98,1) -> #REF! | ... W98: =ROUND(COM!S98,1) -> #REF! | X98: =M98+O98+Q98+S98+U98+W98 -> #REF!
A99: 311 | B99: 37 | C99: 920 | D99: 70769 | E99: КфВ | F99: Проект «Здравоохранение и социальная защита» - 3, 4 (КфВ) (грант) | G99: BMZ ID: 2011 70 190/2013 70 030/2015 70 084 | L99: =ROUND(COM!H99,1) -> #REF! | M99: =ROUND(COM!I99,1) -> #REF! | N99: =ROUND(COM!J99,1) -> #REF! | O99: =ROUND(COM!K99,1) -> #REF! | P99: =ROUND(COM!L99,1) -> #REF! | Q99: =ROUND(COM!M99,1) -> #REF! | R99: =ROUND(COM!N99,1) -> #REF! | S99: =ROUND(COM!O99,1) -> #REF! | ... W99: =ROUND(COM!S99,1) -> #REF! | X99: =M99+O99+Q99+S99+U99+W99 -> #REF!
A100: 311 | B100: 37 | C100: 910 | D100: 70769 | F100: Борьба с туберкулезом-V (КфВ) | L100: =ROUND(COM!H100,1) -> #REF! | M100: =ROUND(COM!I100,1) -> #REF! | N100: =ROUND(COM!J100,1) -> #REF! | O100: =ROUND(COM!K100,1) -> #REF! | P100: =ROUND(COM!L100,1) -> #REF! | Q100: =ROUND(COM!M100,1) -> #REF! | R100: =ROUND(COM!N100,1) -> #REF! | S100: =ROUND(COM!O100,1) -> #REF! | ... W100: =ROUND(COM!S100,1) -> #REF! | X100: =M100+O100+Q100+S100+U100+W100 -> #REF!
A101: 311 | B101: 37 | C101: 920 | D101: 70769 | E101: КфВ | F101: Борьба с туберкулезом-V (КфВ) (грант) | L101: =ROUND(COM!H101,1) -> #REF! | M101: =ROUND(COM!I101,1) -> #REF! | N101: =ROUND(COM!J101,1) -> #REF! | O101: =ROUND(COM!K101,1) -> #REF! | P101: =ROUND(COM!L101,1) -> #REF! | Q101: =ROUND(COM!M101,1) -> #REF! | R101: =ROUND(COM!N101,1) -> #REF! | S101: =ROUND(COM!O101,1) -> #REF! | ... W101: =ROUND(COM!S101,1) -> #REF! | X101: =M101+O101+Q101+S101+U101+W101 -> #REF!
A102: 311 | B102: 37 | C102: 910 | D102: 70769 | F102: Охрана материнства и детства IV-V (КфВ) | L102: =ROUND(COM!H102,1) -> #REF! | M102: =ROUND(COM!I102,1) -> #REF! | N102: =ROUND(COM!J102,1) -> #REF! | O102: =ROUND(COM!K102,1) -> #REF! | P102: =ROUND(COM!L102,1) -> #REF! | Q102: =ROUND(COM!M102,1) -> #REF! | R102: =ROUND(COM!N102,1) -> #REF! | S102: =ROUND(COM!O102,1) -> #REF! | ... W102: =ROUND(COM!S102,1) -> #REF! | X102: =M102+O102+Q102+S102+U102+W102 -> #REF!
A103: 311 | B103: 37 | C103: 920 | D103: 70769 | E103: КфВ | F103: Охрана материнства и детства IV-V (КфВ) (грант) | G103: BMZ ID: 2007 66 543/2007 70 388/2009 66 622/2009 70 301 | L103: =ROUND(COM!H103,1) -> #REF! | M103: =ROUND(COM!I103,1) -> #REF! | N103: =ROUND(COM!J103,1) -> #REF! | O103: =ROUND(COM!K103,1) -> #REF! | P103: =ROUND(COM!L103,1) -> #REF! | Q103: =ROUND(COM!M103,1) -> #REF! | R103: =ROUND(COM!N103,1) -> #REF! | S103: =ROUND(COM!O103,1) -> #REF! | ... W103: =ROUND(COM!S103,1) -> #REF! | X103: =M103+O103+Q103+S103+U103+W103 -> #REF!
A104: 311 | B104: 37 | C104: 930 | D104: 70769 | E104: СФР | F104: Строительство нового корпуса для Городской детской клинической больницы скорой медицинской помощи города Бишкек (СФР) (кредит) | G104: 4/697 | L104: =ROUND(COM!H104,1) -> #REF! | M104: =ROUND(COM!I104,1) -> #REF! | N104: =ROUND(COM!J104,1) -> #REF! | O104: =ROUND(COM!K104,1) -> #REF! | P104: =ROUND(COM!L104,1) -> #REF! | Q104: =ROUND(COM!M104,1) -> #REF! | R104: =ROUND(COM!N104,1) -> #REF! | S104: =ROUND(COM!O104,1) -> #REF! | ... W104: =ROUND(COM!S104,1) -> #REF! | X104: =M104+O104+Q104+S104+U104+W104 -> #REF!
A105: 311 | B105: 37 | C105: 910 | D105: 70769 | F105: Строительство и оснащение нейрохирургического центра Национального госпиталя (КФАЭР) | L105: =ROUND(COM!H105,1) -> #REF! | M105: =ROUND(COM!I105,1) -> #REF! | N105: =ROUND(COM!J105,1) -> #REF! | O105: =ROUND(COM!K105,1) -> #REF! | P105: =ROUND(COM!L105,1) -> #REF! | Q105: =ROUND(COM!M105,1) -> #REF! | R105: =ROUND(COM!N105,1) -> #REF! | S105: =ROUND(COM!O105,1) -> #REF! | ... W105: =ROUND(COM!S105,1) -> #REF! | X105: =M105+O105+Q105+S105+U105+W105 -> #REF!
A106: 311 | B106: 37 | C106: 930 | D106: 70769 | E106: КФАЭР | F106: Строительство и оснащение нейрохирургического центра Национального госпиталя (КФАЭР) (кредит) | L106: =ROUND(COM!H106,1) -> #REF! | M106: =ROUND(COM!I106,1) -> #REF! | N106: =ROUND(COM!J106,1) -> #REF! | O106: =ROUND(COM!K106,1) -> #REF! | P106: =ROUND(COM!L106,1) -> #REF! | Q106: =ROUND(COM!M106,1) -> #REF! | R106: =ROUND(COM!N106,1) -> #REF! | S106: =ROUND(COM!O106,1) -> #REF! | ... W106: =ROUND(COM!S106,1) -> #REF! | X106: =M106+O106+Q106+S106+U106+W106 -> #REF!
A107: 311 | B107: 37 | C107: 920 | D107: 70769 | E107: КфВ | F107: Программа «Охрана материнства и детства» фаза VI-VIII г.Ош (КфВ) (грант) | G107: BMZID:2011 66 453/2012 67 368/2013 65 451/2013 70 022 | L107: =ROUND(COM!H107,1) -> #REF! | M107: =ROUND(COM!I107,1) -> #REF! | N107: =ROUND(COM!J107,1) -> #REF! | O107: =ROUND(COM!K107,1) -> #REF! | P107: =ROUND(COM!L107,1) -> #REF! | Q107: =ROUND(COM!M107,1) -> #REF! | R107: =ROUND(COM!N107,1) -> #REF! | S107: =ROUND(COM!O107,1) -> #REF! | ... W107: =ROUND(COM!S107,1) -> #REF! | X107: =M107+O107+Q107+S107+U107+W107 -> #REF!
A108: 311 | B108: 37 | C108: 920 | D108: 70769 | E108: КфВ | F108: Программа «Охрана материнства и детства» фаза IХ г.Талас (КфВ) (грант) | G108: BMZ ID:2013 67 275/2013 67 283 | L108: =ROUND(COM!H108,1) -> #REF! | M108: =ROUND(COM!I108,1) -> #REF! | N108: =ROUND(COM!J108,1) -> #REF! | O108: =ROUND(COM!K108,1) -> #REF! | P108: =ROUND(COM!L108,1) -> #REF! | Q108: =ROUND(COM!M108,1) -> #REF! | R108: =ROUND(COM!N108,1) -> #REF! | S108: =ROUND(COM!O108,1) -> #REF! | ... W108: =ROUND(COM!S108,1) -> #REF! | X108: =M108+O108+Q108+S108+U108+W108 -> #REF!
...
